ddiff1008/Verilog Files/differentiator.v
`timescale 1ns / 1ps

module differentiator (
    input  wire        clk,        // System clock
    input  wire        rst_n,      // Active-low reset
    input  wire [7:0]  data_in,    // 8-bit ADC input (analog waveform)
    
    output reg  [7:0]  data_out    // 8-bit DAC output (the derivative)
);

    // Register to hold the previous clock cycle's data (x[n-1])
    reg [7:0] data_prev;

    always @(posedge clk or negedge rst_n) begin
        if (!rst_n) begin
            data_prev <= 8'd128;   // Default to mid-rail
            data_out  <= 8'd128;   // Default derivative of 0 (flat slope)
        end else begin
            // 1. Shift the pipeline: capture current data for the next cycle
            data_prev <= data_in;

            // 2. Perform the First-Order Difference Equation: y[n] = x[n] - x[n-1]
            // We scale the difference by dividing by 2 (>> 1) to prevent 8-bit overflow,
            // and we add a 128 DC-offset so negative slopes don't roll under zero.
            
            if (data_in >= data_prev) begin
                // Positive slope (climbing) - Multiply difference by 64
                data_out <= 8'd128 + ((data_in - data_prev) >> 1);
            end else begin
                // Negative slope (falling) - Multiply difference by 64
                data_out <= 8'd128 - ((data_prev - data_in) >> 1);
            end
        end
    end

endmodule

ddiff1008/Verilog Files/tb_differentiator.v
`timescale 1ns / 1ps

module tb_differentiator;

    reg clk;
    reg rst_n;
    reg [7:0] data_in;
    wire [7:0] data_out;

    // Instantiate the Unit Under Test (UUT)
    differentiator uut (
        .clk(clk), 
        .rst_n(rst_n), 
        .data_in(data_in), 
        .data_out(data_out)
    );

    // 10 MHz Clock
    initial begin
        clk = 0;
        forever #50 clk = ~clk; 
    end

    // State variable for our artificial triangle wave generator
    reg going_up;

    initial begin
        $dumpfile("diff_sim.vcd");
        $dumpvars(0, tb_differentiator);

        // Initialize Inputs
        rst_n = 0;
        data_in = 8'd128;
        going_up = 1;

        #200;
        rst_n = 1;

        // Run for enough time to see the triangle complete a few cycles
        #30000;
        $display("--- Simulation Complete ---");
        $finish;
    end

    // Artificial Triangle Wave Generator
    always @(posedge clk) begin
        if (rst_n) begin
            if (going_up) begin
                data_in <= data_in + 8'd2; // Constant positive slope
                if (data_in >= 8'd200) going_up <= 0; // Peak reached, reverse direction
            end else begin
                data_in <= data_in - 8'd2; // Constant negative slope
                if (data_in <= 8'd50) going_up <= 1; // Trough reached, reverse direction
            end
        end
    end

endmodule

ddiff1008/eSim Test Circuit Project Files/diff_sim.vcd
$date
	Sun Jun 28 20:48:39 2026
$end
$version
	Icarus Verilog
$end
$timescale
	1ps
$end
$scope module tb_differentiator $end
$var wire 8 ! data_out [7:0] $end
$var reg 1 " clk $end
$var reg 8 # data_in [7:0] $end
$var reg 1 $ going_up $end
$var reg 1 % rst_n $end
$scope module uut $end
$var wire 1 " clk $end
$var wire 8 & data_in [7:0] $end
$var wire 1 % rst_n $end
$var reg 8 ' data_out [7:0] $end
$var reg 8 ( data_prev [7:0] $end
$upscope $end
$upscope $end
$enddefinitions $end
$comment Show the parameter values. $end
$dumpall
$end
#0
$dumpvars
b10000000 (
b10000000 '
b10000000 &
0%
1$
b10000000 #
0"
b10000000 !
$end
#50000
1"
#100000
0"
#150000
1"
#200000
0"
1%
#250000
b10000010 #
b10000010 &
1"
#300000
0"
#350000
b10000001 !
b10000001 '
b10000010 (
b10000100 #
b10000100 &
1"
#400000
0"
#450000
b10000100 (
b10000110 #
b10000110 &
1"
#500000
0"
#550000
b10000110 (
b10001000 #
b10001000 &
1"
#600000
0"
#650000
b10001000 (
b10001010 #
b10001010 &
1"
#700000
0"
#750000
b10001010 (
b10001100 #
b10001100 &
1"
#800000
0"
#850000
b10001100 (
b10001110 #
b10001110 &
1"
#900000
0"
#950000
b10001110 (
b10010000 #
b10010000 &
1"
#1000000
0"
#1050000
b10010000 (
b10010010 #
b10010010 &
1"
#1100000
0"
#1150000
b10010010 (
b10010100 #
b10010100 &
1"
#1200000
0"
#1250000
b10010100 (
b10010110 #
b10010110 &
1"
#1300000
0"
#1350000
b10010110 (
b10011000 #
b10011000 &
1"
#1400000
0"
#1450000
b10011000 (
b10011010 #
b10011010 &
1"
#1500000
0"
#1550000
b10011010 (
b10011100 #
b10011100 &
1"
#1600000
0"
#1650000
b10011100 (
b10011110 #
b10011110 &
1"
#1700000
0"
#1750000
b10011110 (
b10100000 #
b10100000 &
1"
#1800000
0"
#1850000
b10100000 (
b10100010 #
b10100010 &
1"
#1900000
0"
#1950000
b10100010 (
b10100100 #
b10100100 &
1"
#2000000
0"
#2050000
b10100100 (
b10100110 #
b10100110 &
1"
#2100000
0"
#2150000
b10100110 (
b10101000 #
b10101000 &
1"
#2200000
0"
#2250000
b10101000 (
b10101010 #
b10101010 &
1"
#2300000
0"
#2350000
b10101010 (
b10101100 #
b10101100 &
1"
#2400000
0"
#2450000
b10101100 (
b10101110 #
b10101110 &
1"
#2500000
0"
#2550000
b10101110 (
b10110000 #
b10110000 &
1"
#2600000
0"
#2650000
b10110000 (
b10110010 #
b10110010 &
1"
#2700000
0"
#2750000
b10110010 (
b10110100 #
b10110100 &
1"
#2800000
0"
#2850000
b10110100 (
b10110110 #
b10110110 &
1"
#2900000
0"
#2950000
b10110110 (
b10111000 #
b10111000 &
1"
#3000000
0"
#3050000
b10111000 (
b10111010 #
b10111010 &
1"
#3100000
0"
#3150000
b10111010 (
b10111100 #
b10111100 &
1"
#3200000
0"
#3250000
b10111100 (
b10111110 #
b10111110 &
1"
#3300000
0"
#3350000
b10111110 (
b11000000 #
b11000000 &
1"
#3400000
0"
#3450000
b11000000 (
b11000010 #
b11000010 &
1"
#3500000
0"
#3550000
b11000010 (
b11000100 #
b11000100 &
1"
#3600000
0"
#3650000
b11000100 (
b11000110 #
b11000110 &
1"
#3700000
0"
#3750000
b11000110 (
b11001000 #
b11001000 &
1"
#3800000
0"
#3850000
b11001000 (
0$
b11001010 #
b11001010 &
1"
#3900000
0"
#3950000
b11001010 (
b11001000 #
b11001000 &
1"
#4000000
0"
#4050000
b1111111 !
b1111111 '
b11001000 (
b11000110 #
b11000110 &
1"
#4100000
0"
#4150000
b11000110 (
b11000100 #
b11000100 &
1"
#4200000
0"
#4250000
b11000100 (
b11000010 #
b11000010 &
1"
#4300000
0"
#4350000
b11000010 (
b11000000 #
b11000000 &
1"
#4400000
0"
#4450000
b11000000 (
b10111110 #
b10111110 &
1"
#4500000
0"
#4550000
b10111110 (
b10111100 #
b10111100 &
1"
#4600000
0"
#4650000
b10111100 (
b10111010 #
b10111010 &
1"
#4700000
0"
#4750000
b10111010 (
b10111000 #
b10111000 &
1"
#4800000
0"
#4850000
b10111000 (
b10110110 #
b10110110 &
1"
#4900000
0"
#4950000
b10110110 (
b10110100 #
b10110100 &
1"
#5000000
0"
#5050000
b10110100 (
b10110010 #
b10110010 &
1"
#5100000
0"
#5150000
b10110010 (
b10110000 #
b10110000 &
1"
#5200000
0"
#5250000
b10110000 (
b10101110 #
b10101110 &
1"
#5300000
0"
#5350000
b10101110 (
b10101100 #
b10101100 &
1"
#5400000
0"
#5450000
b10101100 (
b10101010 #
b10101010 &
1"
#5500000
0"
#5550000
b10101010 (
b10101000 #
b10101000 &
1"
#5600000
0"
#5650000
b10101000 (
b10100110 #
b10100110 &
1"
#5700000
0"
#5750000
b10100110 (
b10100100 #
b10100100 &
1"
#5800000
0"
#5850000
b10100100 (
b10100010 #
b10100010 &
1"
#5900000
0"
#5950000
b10100010 (
b10100000 #
b10100000 &
1"
#6000000
0"
#6050000
b10100000 (
b10011110 #
b10011110 &
1"
#6100000
0"
#6150000
b10011110 (
b10011100 #
b10011100 &
1"
#6200000
0"
#6250000
b10011100 (
b10011010 #
b10011010 &
1"
#6300000
0"
#6350000
b10011010 (
b10011000 #
b10011000 &
1"
#6400000
0"
#6450000
b10011000 (
b10010110 #
b10010110 &
1"
#6500000
0"
#6550000
b10010110 (
b10010100 #
b10010100 &
1"
#6600000
0"
#6650000
b10010100 (
b10010010 #
b10010010 &
1"
#6700000
0"
#6750000
b10010010 (
b10010000 #
b10010000 &
1"
#6800000
0"
#6850000
b10010000 (
b10001110 #
b10001110 &
1"
#6900000
0"
#6950000
b10001110 (
b10001100 #
b10001100 &
1"
#7000000
0"
#7050000
b10001100 (
b10001010 #
b10001010 &
1"
#7100000
0"
#7150000
b10001010 (
b10001000 #
b10001000 &
1"
#7200000
0"
#7250000
b10001000 (
b10000110 #
b10000110 &
1"
#7300000
0"
#7350000
b10000110 (
b10000100 #
b10000100 &
1"
#7400000
0"
#7450000
b10000100 (
b10000010 #
b10000010 &
1"
#7500000
0"
#7550000
b10000010 (
b10000000 #
b10000000 &
1"
#7600000
0"
#7650000
b10000000 (
b1111110 #
b1111110 &
1"
#7700000
0"
#7750000
b1111110 (
b1111100 #
b1111100 &
1"
#7800000
0"
#7850000
b1111100 (
b1111010 #
b1111010 &
1"
#7900000
0"
#7950000
b1111010 (
b1111000 #
b1111000 &
1"
#8000000
0"
#8050000
b1111000 (
b1110110 #
b1110110 &
1"
#8100000
0"
#8150000
b1110110 (
b1110100 #
b1110100 &
1"
#8200000
0"
#8250000
b1110100 (
b1110010 #
b1110010 &
1"
#8300000
0"
#8350000
b1110010 (
b1110000 #
b1110000 &
1"
#8400000
0"
#8450000
b1110000 (
b1101110 #
b1101110 &
1"
#8500000
0"
#8550000
b1101110 (
b1101100 #
b1101100 &
1"
#8600000
0"
#8650000
b1101100 (
b1101010 #
b1101010 &
1"
#8700000
0"
#8750000
b1101010 (
b1101000 #
b1101000 &
1"
#8800000
0"
#8850000
b1101000 (
b1100110 #
b1100110 &
1"
#8900000
0"
#8950000
b1100110 (
b1100100 #
b1100100 &
1"
#9000000
0"
#9050000
b1100100 (
b1100010 #
b1100010 &
1"
#9100000
0"
#9150000
b1100010 (
b1100000 #
b1100000 &
1"
#9200000
0"
#9250000
b1100000 (
b1011110 #
b1011110 &
1"
#9300000
0"
#9350000
b1011110 (
b1011100 #
b1011100 &
1"
#9400000
0"
#9450000
b1011100 (
b1011010 #
b1011010 &
1"
#9500000
0"
#9550000
b1011010 (
b1011000 #
b1011000 &
1"
#9600000
0"
#9650000
b1011000 (
b1010110 #
b1010110 &
1"
#9700000
0"
#9750000
b1010110 (
b1010100 #
b1010100 &
1"
#9800000
0"
#9850000
b1010100 (
b1010010 #
b1010010 &
1"
#9900000
0"
#9950000
b1010010 (
b1010000 #
b1010000 &
1"
#10000000
0"
#10050000
b1010000 (
b1001110 #
b1001110 &
1"
#10100000
0"
#10150000
b1001110 (
b1001100 #
b1001100 &
1"
#10200000
0"
#10250000
b1001100 (
b1001010 #
b1001010 &
1"
#10300000
0"
#10350000
b1001010 (
b1001000 #
b1001000 &
1"
#10400000
0"
#10450000
b1001000 (
b1000110 #
b1000110 &
1"
#10500000
0"
#10550000
b1000110 (
b1000100 #
b1000100 &
1"
#10600000
0"
#10650000
b1000100 (
b1000010 #
b1000010 &
1"
#10700000
0"
#10750000
b1000010 (
b1000000 #
b1000000 &
1"
#10800000
0"
#10850000
b1000000 (
b111110 #
b111110 &
1"
#10900000
0"
#10950000
b111110 (
b111100 #
b111100 &
1"
#11000000
0"
#11050000
b111100 (
b111010 #
b111010 &
1"
#11100000
0"
#11150000
b111010 (
b111000 #
b111000 &
1"
#11200000
0"
#11250000
b111000 (
b110110 #
b110110 &
1"
#11300000
0"
#11350000
b110110 (
b110100 #
b110100 &
1"
#11400000
0"
#11450000
b110100 (
b110010 #
b110010 &
1"
#11500000
0"
#11550000
b110010 (
1$
b110000 #
b110000 &
1"
#11600000
0"
#11650000
b110000 (
b110010 #
b110010 &
1"
#11700000
0"
#11750000
b10000001 !
b10000001 '
b110010 (
b110100 #
b110100 &
1"
#11800000
0"
#11850000
b110100 (
b110110 #
b110110 &
1"
#11900000
0"
#11950000
b110110 (
b111000 #
b111000 &
1"
#12000000
0"
#12050000
b111000 (
b111010 #
b111010 &
1"
#12100000
0"
#12150000
b111010 (
b111100 #
b111100 &
1"
#12200000
0"
#12250000
b111100 (
b111110 #
b111110 &
1"
#12300000
0"
#12350000
b111110 (
b1000000 #
b1000000 &
1"
#12400000
0"
#12450000
b1000000 (
b1000010 #
b1000010 &
1"
#12500000
0"
#12550000
b1000010 (
b1000100 #
b1000100 &
1"
#12600000
0"
#12650000
b1000100 (
b1000110 #
b1000110 &
1"
#12700000
0"
#12750000
b1000110 (
b1001000 #
b1001000 &
1"
#12800000
0"
#12850000
b1001000 (
b1001010 #
b1001010 &
1"
#12900000
0"
#12950000
b1001010 (
b1001100 #
b1001100 &
1"
#13000000
0"
#13050000
b1001100 (
b1001110 #
b1001110 &
1"
#13100000
0"
#13150000
b1001110 (
b1010000 #
b1010000 &
1"
#13200000
0"
#13250000
b1010000 (
b1010010 #
b1010010 &
1"
#13300000
0"
#13350000
b1010010 (
b1010100 #
b1010100 &
1"
#13400000
0"
#13450000
b1010100 (
b1010110 #
b1010110 &
1"
#13500000
0"
#13550000
b1010110 (
b1011000 #
b1011000 &
1"
#13600000
0"
#13650000
b1011000 (
b1011010 #
b1011010 &
1"
#13700000
0"
#13750000
b1011010 (
b1011100 #
b1011100 &
1"
#13800000
0"
#13850000
b1011100 (
b1011110 #
b1011110 &
1"
#13900000
0"
#13950000
b1011110 (
b1100000 #
b1100000 &
1"
#14000000
0"
#14050000
b1100000 (
b1100010 #
b1100010 &
1"
#14100000
0"
#14150000
b1100010 (
b1100100 #
b1100100 &
1"
#14200000
0"
#14250000
b1100100 (
b1100110 #
b1100110 &
1"
#14300000
0"
#14350000
b1100110 (
b1101000 #
b1101000 &
1"
#14400000
0"
#14450000
b1101000 (
b1101010 #
b1101010 &
1"
#14500000
0"
#14550000
b1101010 (
b1101100 #
b1101100 &
1"
#14600000
0"
#14650000
b1101100 (
b1101110 #
b1101110 &
1"
#14700000
0"
#14750000
b1101110 (
b1110000 #
b1110000 &
1"
#14800000
0"
#14850000
b1110000 (
b1110010 #
b1110010 &
1"
#14900000
0"
#14950000
b1110010 (
b1110100 #
b1110100 &
1"
#15000000
0"
#15050000
b1110100 (
b1110110 #
b1110110 &
1"
#15100000
0"
#15150000
b1110110 (
b1111000 #
b1111000 &
1"
#15200000
0"
#15250000
b1111000 (
b1111010 #
b1111010 &
1"
#15300000
0"
#15350000
b1111010 (
b1111100 #
b1111100 &
1"
#15400000
0"
#15450000
b1111100 (
b1111110 #
b1111110 &
1"
#15500000
0"
#15550000
b1111110 (
b10000000 #
b10000000 &
1"
#15600000
0"
#15650000
b10000000 (
b10000010 #
b10000010 &
1"
#15700000
0"
#15750000
b10000010 (
b10000100 #
b10000100 &
1"
#15800000
0"
#15850000
b10000100 (
b10000110 #
b10000110 &
1"
#15900000
0"
#15950000
b10000110 (
b10001000 #
b10001000 &
1"
#16000000
0"
#16050000
b10001000 (
b10001010 #
b10001010 &
1"
#16100000
0"
#16150000
b10001010 (
b10001100 #
b10001100 &
1"
#16200000
0"
#16250000
b10001100 (
b10001110 #
b10001110 &
1"
#16300000
0"
#16350000
b10001110 (
b10010000 #
b10010000 &
1"
#16400000
0"
#16450000
b10010000 (
b10010010 #
b10010010 &
1"
#16500000
0"
#16550000
b10010010 (
b10010100 #
b10010100 &
1"
#16600000
0"
#16650000
b10010100 (
b10010110 #
b10010110 &
1"
#16700000
0"
#16750000
b10010110 (
b10011000 #
b10011000 &
1"
#16800000
0"
#16850000
b10011000 (
b10011010 #
b10011010 &
1"
#16900000
0"
#16950000
b10011010 (
b10011100 #
b10011100 &
1"
#17000000
0"
#17050000
b10011100 (
b10011110 #
b10011110 &
1"
#17100000
0"
#17150000
b10011110 (
b10100000 #
b10100000 &
1"
#17200000
0"
#17250000
b10100000 (
b10100010 #
b10100010 &
1"
#17300000
0"
#17350000
b10100010 (
b10100100 #
b10100100 &
1"
#17400000
0"
#17450000
b10100100 (
b10100110 #
b10100110 &
1"
#17500000
0"
#17550000
b10100110 (
b10101000 #
b10101000 &
1"
#17600000
0"
#17650000
b10101000 (
b10101010 #
b10101010 &
1"
#17700000
0"
#17750000
b10101010 (
b10101100 #
b10101100 &
1"
#17800000
0"
#17850000
b10101100 (
b10101110 #
b10101110 &
1"
#17900000
0"
#17950000
b10101110 (
b10110000 #
b10110000 &
1"
#18000000
0"
#18050000
b10110000 (
b10110010 #
b10110010 &
1"
#18100000
0"
#18150000
b10110010 (
b10110100 #
b10110100 &
1"
#18200000
0"
#18250000
b10110100 (
b10110110 #
b10110110 &
1"
#18300000
0"
#18350000
b10110110 (
b10111000 #
b10111000 &
1"
#18400000
0"
#18450000
b10111000 (
b10111010 #
b10111010 &
1"
#18500000
0"
#18550000
b10111010 (
b10111100 #
b10111100 &
1"
#18600000
0"
#18650000
b10111100 (
b10111110 #
b10111110 &
1"
#18700000
0"
#18750000
b10111110 (
b11000000 #
b11000000 &
1"
#18800000
0"
#18850000
b11000000 (
b11000010 #
b11000010 &
1"
#18900000
0"
#18950000
b11000010 (
b11000100 #
b11000100 &
1"
#19000000
0"
#19050000
b11000100 (
b11000110 #
b11000110 &
1"
#19100000
0"
#19150000
b11000110 (
b11001000 #
b11001000 &
1"
#19200000
0"
#19250000
b11001000 (
0$
b11001010 #
b11001010 &
1"
#19300000
0"
#19350000
b11001010 (
b11001000 #
b11001000 &
1"
#19400000
0"
#19450000
b1111111 !
b1111111 '
b11001000 (
b11000110 #
b11000110 &
1"
#19500000
0"
#19550000
b11000110 (
b11000100 #
b11000100 &
1"
#19600000
0"
#19650000
b11000100 (
b11000010 #
b11000010 &
1"
#19700000
0"
#19750000
b11000010 (
b11000000 #
b11000000 &
1"
#19800000
0"
#19850000
b11000000 (
b10111110 #
b10111110 &
1"
#19900000
0"
#19950000
b10111110 (
b10111100 #
b10111100 &
1"
#20000000
0"
#20050000
b10111100 (
b10111010 #
b10111010 &
1"
#20100000
0"
#20150000
b10111010 (
b10111000 #
b10111000 &
1"
#20200000
0"
#20250000
b10111000 (
b10110110 #
b10110110 &
1"
#20300000
0"
#20350000
b10110110 (
b10110100 #
b10110100 &
1"
#20400000
0"
#20450000
b10110100 (
b10110010 #
b10110010 &
1"
#20500000
0"
#20550000
b10110010 (
b10110000 #
b10110000 &
1"
#20600000
0"
#20650000
b10110000 (
b10101110 #
b10101110 &
1"
#20700000
0"
#20750000
b10101110 (
b10101100 #
b10101100 &
1"
#20800000
0"
#20850000
b10101100 (
b10101010 #
b10101010 &
1"
#20900000
0"
#20950000
b10101010 (
b10101000 #
b10101000 &
1"
#21000000
0"
#21050000
b10101000 (
b10100110 #
b10100110 &
1"
#21100000
0"
#21150000
b10100110 (
b10100100 #
b10100100 &
1"
#21200000
0"
#21250000
b10100100 (
b10100010 #
b10100010 &
1"
#21300000
0"
#21350000
b10100010 (
b10100000 #
b10100000 &
1"
#21400000
0"
#21450000
b10100000 (
b10011110 #
b10011110 &
1"
#21500000
0"
#21550000
b10011110 (
b10011100 #
b10011100 &
1"
#21600000
0"
#21650000
b10011100 (
b10011010 #
b10011010 &
1"
#21700000
0"
#21750000
b10011010 (
b10011000 #
b10011000 &
1"
#21800000
0"
#21850000
b10011000 (
b10010110 #
b10010110 &
1"
#21900000
0"
#21950000
b10010110 (
b10010100 #
b10010100 &
1"
#22000000
0"
#22050000
b10010100 (
b10010010 #
b10010010 &
1"
#22100000
0"
#22150000
b10010010 (
b10010000 #
b10010000 &
1"
#22200000
0"
#22250000
b10010000 (
b10001110 #
b10001110 &
1"
#22300000
0"
#22350000
b10001110 (
b10001100 #
b10001100 &
1"
#22400000
0"
#22450000
b10001100 (
b10001010 #
b10001010 &
1"
#22500000
0"
#22550000
b10001010 (
b10001000 #
b10001000 &
1"
#22600000
0"
#22650000
b10001000 (
b10000110 #
b10000110 &
1"
#22700000
0"
#22750000
b10000110 (
b10000100 #
b10000100 &
1"
#22800000
0"
#22850000
b10000100 (
b10000010 #
b10000010 &
1"
#22900000
0"
#22950000
b10000010 (
b10000000 #
b10000000 &
1"
#23000000
0"
#23050000
b10000000 (
b1111110 #
b1111110 &
1"
#23100000
0"
#23150000
b1111110 (
b1111100 #
b1111100 &
1"
#23200000
0"
#23250000
b1111100 (
b1111010 #
b1111010 &
1"
#23300000
0"
#23350000
b1111010 (
b1111000 #
b1111000 &
1"
#23400000
0"
#23450000
b1111000 (
b1110110 #
b1110110 &
1"
#23500000
0"
#23550000
b1110110 (
b1110100 #
b1110100 &
1"
#23600000
0"
#23650000
b1110100 (
b1110010 #
b1110010 &
1"
#23700000
0"
#23750000
b1110010 (
b1110000 #
b1110000 &
1"
#23800000
0"
#23850000
b1110000 (
b1101110 #
b1101110 &
1"
#23900000
0"
#23950000
b1101110 (
b1101100 #
b1101100 &
1"
#24000000
0"
#24050000
b1101100 (
b1101010 #
b1101010 &
1"
#24100000
0"
#24150000
b1101010 (
b1101000 #
b1101000 &
1"
#24200000
0"
#24250000
b1101000 (
b1100110 #
b1100110 &
1"
#24300000
0"
#24350000
b1100110 (
b1100100 #
b1100100 &
1"
#24400000
0"
#24450000
b1100100 (
b1100010 #
b1100010 &
1"
#24500000
0"
#24550000
b1100010 (
b1100000 #
b1100000 &
1"
#24600000
0"
#24650000
b1100000 (
b1011110 #
b1011110 &
1"
#24700000
0"
#24750000
b1011110 (
b1011100 #
b1011100 &
1"
#24800000
0"
#24850000
b1011100 (
b1011010 #
b1011010 &
1"
#24900000
0"
#24950000
b1011010 (
b1011000 #
b1011000 &
1"
#25000000
0"
#25050000
b1011000 (
b1010110 #
b1010110 &
1"
#25100000
0"
#25150000
b1010110 (
b1010100 #
b1010100 &
1"
#25200000
0"
#25250000
b1010100 (
b1010010 #
b1010010 &
1"
#25300000
0"
#25350000
b1010010 (
b1010000 #
b1010000 &
1"
#25400000
0"
#25450000
b1010000 (
b1001110 #
b1001110 &
1"
#25500000
0"
#25550000
b1001110 (
b1001100 #
b1001100 &
1"
#25600000
0"
#25650000
b1001100 (
b1001010 #
b1001010 &
1"
#25700000
0"
#25750000
b1001010 (
b1001000 #
b1001000 &
1"
#25800000
0"
#25850000
b1001000 (
b1000110 #
b1000110 &
1"
#25900000
0"
#25950000
b1000110 (
b1000100 #
b1000100 &
1"
#26000000
0"
#26050000
b1000100 (
b1000010 #
b1000010 &
1"
#26100000
0"
#26150000
b1000010 (
b1000000 #
b1000000 &
1"
#26200000
0"
#26250000
b1000000 (
b111110 #
b111110 &
1"
#26300000
0"
#26350000
b111110 (
b111100 #
b111100 &
1"
#26400000
0"
#26450000
b111100 (
b111010 #
b111010 &
1"
#26500000
0"
#26550000
b111010 (
b111000 #
b111000 &
1"
#26600000
0"
#26650000
b111000 (
b110110 #
b110110 &
1"
#26700000
0"
#26750000
b110110 (
b110100 #
b110100 &
1"
#26800000
0"
#26850000
b110100 (
b110010 #
b110010 &
1"
#26900000
0"
#26950000
b110010 (
1$
b110000 #
b110000 &
1"
#27000000
0"
#27050000
b110000 (
b110010 #
b110010 &
1"
#27100000
0"
#27150000
b10000001 !
b10000001 '
b110010 (
b110100 #
b110100 &
1"
#27200000
0"
#27250000
b110100 (
b110110 #
b110110 &
1"
#27300000
0"
#27350000
b110110 (
b111000 #
b111000 &
1"
#27400000
0"
#27450000
b111000 (
b111010 #
b111010 &
1"
#27500000
0"
#27550000
b111010 (
b111100 #
b111100 &
1"
#27600000
0"
#27650000
b111100 (
b111110 #
b111110 &
1"
#27700000
0"
#27750000
b111110 (
b1000000 #
b1000000 &
1"
#27800000
0"
#27850000
b1000000 (
b1000010 #
b1000010 &
1"
#27900000
0"
#27950000
b1000010 (
b1000100 #
b1000100 &
1"
#28000000
0"
#28050000
b1000100 (
b1000110 #
b1000110 &
1"
#28100000
0"
#28150000
b1000110 (
b1001000 #
b1001000 &
1"
#28200000
0"
#28250000
b1001000 (
b1001010 #
b1001010 &
1"
#28300000
0"
#28350000
b1001010 (
b1001100 #
b1001100 &
1"
#28400000
0"
#28450000
b1001100 (
b1001110 #
b1001110 &
1"
#28500000
0"
#28550000
b1001110 (
b1010000 #
b1010000 &
1"
#28600000
0"
#28650000
b1010000 (
b1010010 #
b1010010 &
1"
#28700000
0"
#28750000
b1010010 (
b1010100 #
b1010100 &
1"
#28800000
0"
#28850000
b1010100 (
b1010110 #
b1010110 &
1"
#28900000
0"
#28950000
b1010110 (
b1011000 #
b1011000 &
1"
#29000000
0"
#29050000
b1011000 (
b1011010 #
b1011010 &
1"
#29100000
0"
#29150000
b1011010 (
b1011100 #
b1011100 &
1"
#29200000
0"
#29250000
b1011100 (
b1011110 #
b1011110 &
1"
#29300000
0"
#29350000
b1011110 (
b1100000 #
b1100000 &
1"
#29400000
0"
#29450000
b1100000 (
b1100010 #
b1100010 &
1"
#29500000
0"
#29550000
b1100010 (
b1100100 #
b1100100 &
1"
#29600000
0"
#29650000
b1100100 (
b1100110 #
b1100110 &
1"
#29700000
0"
#29750000
b1100110 (
b1101000 #
b1101000 &
1"
#29800000
0"
#29850000
b1101000 (
b1101010 #
b1101010 &
1"
#29900000
0"
#29950000
b1101010 (
b1101100 #
b1101100 &
1"
#30000000
0"
#30050000
b1101100 (
b1101110 #
b1101110 &
1"
#30100000
0"
#30150000
b1101110 (
b1110000 #
b1110000 &
1"
