dds1808/Verilog Files/dds_sine.v
`timescale 1ns / 1ps

module dds_sine (
    input  wire        clk,          // High-speed system clock
    input  wire        rst_n,        // Active-low asynchronous reset
    input  wire [15:0] tuning_word,  // Controls the output frequency
    
    output reg  [7:0]  sine_out      // 8-bit Digital Sine Wave Output
);

    //------------------------------------------------------------------------
    // 1. THE PHASE ACCUMULATOR
    //------------------------------------------------------------------------
    reg [15:0] phase_acc;

    always @(posedge clk or negedge rst_n) begin
        if (!rst_n) begin
            phase_acc <= 16'd0;
        end else begin
            // Continuously add the tuning word. 
            // It will naturally overflow and wrap around, creating a sawtooth phase.
            phase_acc <= phase_acc + tuning_word;
        end
    end

    // Extract the top 5 bits of the accumulator to act as our LUT address (0 to 31)
    wire [4:0] lut_index = phase_acc[15:11];

    //------------------------------------------------------------------------
    // 2. THE SINE WAVE LOOKUP TABLE (LUT)
    //------------------------------------------------------------------------
    // This combinational block maps the linear phase (0 to 31) into 
    // a non-linear sine wave amplitude (0 to 255) using pre-calculated values.
    
    always @(*) begin
        case (lut_index)
            // Quadrant 1 (0 to 90 degrees)
            5'd0  : sine_out = 8'd128;
            5'd1  : sine_out = 8'd153;
            5'd2  : sine_out = 8'd177;
            5'd3  : sine_out = 8'd199;
            5'd4  : sine_out = 8'd218;
            5'd5  : sine_out = 8'd234;
            5'd6  : sine_out = 8'd246;
            5'd7  : sine_out = 8'd253;
            
            // Quadrant 2 (90 to 180 degrees)
            5'd8  : sine_out = 8'd255; // Peak Positive
            5'd9  : sine_out = 8'd253;
            5'd10 : sine_out = 8'd246;
            5'd11 : sine_out = 8'd234;
            5'd12 : sine_out = 8'd218;
            5'd13 : sine_out = 8'd199;
            5'd14 : sine_out = 8'd177;
            5'd15 : sine_out = 8'd153;
            
            // Quadrant 3 (180 to 270 degrees)
            5'd16 : sine_out = 8'd128; // Zero Crossing
            5'd17 : sine_out = 8'd103;
            5'd18 : sine_out = 8'd79;
            5'd19 : sine_out = 8'd57;
            5'd20 : sine_out = 8'd38;
            5'd21 : sine_out = 8'd22;
            5'd22 : sine_out = 8'd10;
            5'd23 : sine_out = 8'd3;
            
            // Quadrant 4 (270 to 360 degrees)
            5'd24 : sine_out = 8'd0;   // Peak Negative
            5'd25 : sine_out = 8'd3;
            5'd26 : sine_out = 8'd10;
            5'd27 : sine_out = 8'd22;
            5'd28 : sine_out = 8'd38;
            5'd29 : sine_out = 8'd57;
            5'd30 : sine_out = 8'd79;
            5'd31 : sine_out = 8'd103;
            
            default : sine_out = 8'd128; // Safe fallback
        endcase
    end

endmodule

dds1808/Verilog Files/tb_dds_sine.v
`timescale 1ns / 1ps

module tb_dds_sine;

    // Inputs
    reg clk;
    reg rst_n;
    reg [15:0] tuning_word;

    // Outputs
    wire [7:0] sine_out;

    // Instantiate the Unit Under Test (UUT)
    dds_sine uut (
        .clk(clk), 
        .rst_n(rst_n), 
        .tuning_word(tuning_word), 
        .sine_out(sine_out)
    );

    // Generate 10 MHz System Clock (100ns period -> 50ns half-period)
    initial begin
        clk = 0;
        forever #50 clk = ~clk;
    end

    // Main Test Stimulus
    initial begin
        // Setup GTKWave Output
        $dumpfile("dds_sim.vcd");
        $dumpvars(0, tb_dds_sine);

        // Initialize Inputs
        rst_n = 0;
        tuning_word = 16'd0;

        // Release Reset
        #200;
        rst_n = 1;
        $display("--- Starting DDS Synthesizer Simulation ---");

        // 1. Slow Frequency Sine Wave
        tuning_word = 16'd500; 
        #50000; // Let it run long enough to draw a few full waves

        // 2. Fast Frequency Sine Wave (4x faster)
        tuning_word = 16'd2000;
        #50000;
        
        $display("--- Simulation Complete ---");
        $finish;
    end

endmodule

dds1808/eSim Test Circuit Project Files/dds_sim.vcd
$date
	Thu Jun 11 18:32:37 2026
$end
$version
	Icarus Verilog
$end
$timescale
	1ps
$end
$scope module tb_dds_sine $end
$var wire 8 ! sine_out [7:0] $end
$var reg 1 " clk $end
$var reg 1 # rst_n $end
$var reg 16 $ tuning_word [15:0] $end
$scope module uut $end
$var wire 1 " clk $end
$var wire 1 # rst_n $end
$var wire 16 % tuning_word [15:0] $end
$var wire 5 & lut_index [4:0] $end
$var reg 16 ' phase_acc [15:0] $end
$var reg 8 ( sine_out [7:0] $end
$upscope $end
$upscope $end
$enddefinitions $end
$comment Show the parameter values. $end
$dumpall
$end
#0
$dumpvars
b10000000 (
b0 '
b0 &
b0 %
b0 $
0#
0"
b10000000 !
$end
#50000
1"
#100000
0"
#150000
1"
#200000
0"
b111110100 $
b111110100 %
1#
#250000
b111110100 '
1"
#300000
0"
#350000
b1111101000 '
1"
#400000
0"
#450000
b10111011100 '
1"
#500000
0"
#550000
b11111010000 '
1"
#600000
0"
#650000
b10011001 !
b10011001 (
b1 &
b100111000100 '
1"
#700000
0"
#750000
b101110111000 '
1"
#800000
0"
#850000
b110110101100 '
1"
#900000
0"
#950000
b111110100000 '
1"
#1000000
0"
#1050000
b10110001 !
b10110001 (
b10 &
b1000110010100 '
1"
#1100000
0"
#1150000
b1001110001000 '
1"
#1200000
0"
#1250000
b1010101111100 '
1"
#1300000
0"
#1350000
b1011101110000 '
1"
#1400000
0"
#1450000
b11000111 !
b11000111 (
b11 &
b1100101100100 '
1"
#1500000
0"
#1550000
b1101101011000 '
1"
#1600000
0"
#1650000
b1110101001100 '
1"
#1700000
0"
#1750000
b1111101000000 '
1"
#1800000
0"
#1850000
b11011010 !
b11011010 (
b100 &
b10000100110100 '
1"
#1900000
0"
#1950000
b10001100101000 '
1"
#2000000
0"
#2050000
b10010100011100 '
1"
#2100000
0"
#2150000
b10011100010000 '
1"
#2200000
0"
#2250000
b11101010 !
b11101010 (
b101 &
b10100100000100 '
1"
#2300000
0"
#2350000
b10101011111000 '
1"
#2400000
0"
#2450000
b10110011101100 '
1"
#2500000
0"
#2550000
b10111011100000 '
1"
#2600000
0"
#2650000
b11110110 !
b11110110 (
b110 &
b11000011010100 '
1"
#2700000
0"
#2750000
b11001011001000 '
1"
#2800000
0"
#2850000
b11010010111100 '
1"
#2900000
0"
#2950000
b11011010110000 '
1"
#3000000
0"
#3050000
b11111101 !
b11111101 (
b111 &
b11100010100100 '
1"
#3100000
0"
#3150000
b11101010011000 '
1"
#3200000
0"
#3250000
b11110010001100 '
1"
#3300000
0"
#3350000
b11111010000000 '
1"
#3400000
0"
#3450000
b11111111 !
b11111111 (
b1000 &
b100000001110100 '
1"
#3500000
0"
#3550000
b100001001101000 '
1"
#3600000
0"
#3650000
b100010001011100 '
1"
#3700000
0"
#3750000
b100011001010000 '
1"
#3800000
0"
#3850000
b11111101 !
b11111101 (
b1001 &
b100100001000100 '
1"
#3900000
0"
#3950000
b100101000111000 '
1"
#4000000
0"
#4050000
b100110000101100 '
1"
#4100000
0"
#4150000
b100111000100000 '
1"
#4200000
0"
#4250000
b11110110 !
b11110110 (
b1010 &
b101000000010100 '
1"
#4300000
0"
#4350000
b101001000001000 '
1"
#4400000
0"
#4450000
b101001111111100 '
1"
#4500000
0"
#4550000
b101010111110000 '
1"
#4600000
0"
#4650000
b101011111100100 '
1"
#4700000
0"
#4750000
b11101010 !
b11101010 (
b1011 &
b101100111011000 '
1"
#4800000
0"
#4850000
b101101111001100 '
1"
#4900000
0"
#4950000
b101110111000000 '
1"
#5000000
0"
#5050000
b101111110110100 '
1"
#5100000
0"
#5150000
b11011010 !
b11011010 (
b1100 &
b110000110101000 '
1"
#5200000
0"
#5250000
b110001110011100 '
1"
#5300000
0"
#5350000
b110010110010000 '
1"
#5400000
0"
#5450000
b110011110000100 '
1"
#5500000
0"
#5550000
b11000111 !
b11000111 (
b1101 &
b110100101111000 '
1"
#5600000
0"
#5650000
b110101101101100 '
1"
#5700000
0"
#5750000
b110110101100000 '
1"
#5800000
0"
#5850000
b110111101010100 '
1"
#5900000
0"
#5950000
b10110001 !
b10110001 (
b1110 &
b111000101001000 '
1"
#6000000
0"
#6050000
b111001100111100 '
1"
#6100000
0"
#6150000
b111010100110000 '
1"
#6200000
0"
#6250000
b111011100100100 '
1"
#6300000
0"
#6350000
b10011001 !
b10011001 (
b1111 &
b111100100011000 '
1"
#6400000
0"
#6450000
b111101100001100 '
1"
#6500000
0"
#6550000
b111110100000000 '
1"
#6600000
0"
#6650000
b111111011110100 '
1"
#6700000
0"
#6750000
b10000000 !
b10000000 (
b10000 &
b1000000011101000 '
1"
#6800000
0"
#6850000
b1000001011011100 '
1"
#6900000
0"
#6950000
b1000010011010000 '
1"
#7000000
0"
#7050000
b1000011011000100 '
1"
#7100000
0"
#7150000
b1100111 !
b1100111 (
b10001 &
b1000100010111000 '
1"
#7200000
0"
#7250000
b1000101010101100 '
1"
#7300000
0"
#7350000
b1000110010100000 '
1"
#7400000
0"
#7450000
b1000111010010100 '
1"
#7500000
0"
#7550000
b1001111 !
b1001111 (
b10010 &
b1001000010001000 '
1"
#7600000
0"
#7650000
b1001001001111100 '
1"
#7700000
0"
#7750000
b1001010001110000 '
1"
#7800000
0"
#7850000
b1001011001100100 '
1"
#7900000
0"
#7950000
b111001 !
b111001 (
b10011 &
b1001100001011000 '
1"
#8000000
0"
#8050000
b1001101001001100 '
1"
#8100000
0"
#8150000
b1001110001000000 '
1"
#8200000
0"
#8250000
b1001111000110100 '
1"
#8300000
0"
#8350000
b100110 !
b100110 (
b10100 &
b1010000000101000 '
1"
#8400000
0"
#8450000
b1010001000011100 '
1"
#8500000
0"
#8550000
b1010010000010000 '
1"
#8600000
0"
#8650000
b1010011000000100 '
1"
#8700000
0"
#8750000
b1010011111111000 '
1"
#8800000
0"
#8850000
b10110 !
b10110 (
b10101 &
b1010100111101100 '
1"
#8900000
0"
#8950000
b1010101111100000 '
1"
#9000000
0"
#9050000
b1010110111010100 '
1"
#9100000
0"
#9150000
b1010111111001000 '
1"
#9200000
0"
#9250000
b1010 !
b1010 (
b10110 &
b1011000110111100 '
1"
#9300000
0"
#9350000
b1011001110110000 '
1"
#9400000
0"
#9450000
b1011010110100100 '
1"
#9500000
0"
#9550000
b1011011110011000 '
1"
#9600000
0"
#9650000
b11 !
b11 (
b10111 &
b1011100110001100 '
1"
#9700000
0"
#9750000
b1011101110000000 '
1"
#9800000
0"
#9850000
b1011110101110100 '
1"
#9900000
0"
#9950000
b1011111101101000 '
1"
#10000000
0"
#10050000
b0 !
b0 (
b11000 &
b1100000101011100 '
1"
#10100000
0"
#10150000
b1100001101010000 '
1"
#10200000
0"
#10250000
b1100010101000100 '
1"
#10300000
0"
#10350000
b1100011100111000 '
1"
#10400000
0"
#10450000
b11 !
b11 (
b11001 &
b1100100100101100 '
1"
#10500000
0"
#10550000
b1100101100100000 '
1"
#10600000
0"
#10650000
b1100110100010100 '
1"
#10700000
0"
#10750000
b1100111100001000 '
1"
#10800000
0"
#10850000
b1010 !
b1010 (
b11010 &
b1101000011111100 '
1"
#10900000
0"
#10950000
b1101001011110000 '
1"
#11000000
0"
#11050000
b1101010011100100 '
1"
#11100000
0"
#11150000
b1101011011011000 '
1"
#11200000
0"
#11250000
b10110 !
b10110 (
b11011 &
b1101100011001100 '
1"
#11300000
0"
#11350000
b1101101011000000 '
1"
#11400000
0"
#11450000
b1101110010110100 '
1"
#11500000
0"
#11550000
b1101111010101000 '
1"
#11600000
0"
#11650000
b100110 !
b100110 (
b11100 &
b1110000010011100 '
1"
#11700000
0"
#11750000
b1110001010010000 '
1"
#11800000
0"
#11850000
b1110010010000100 '
1"
#11900000
0"
#11950000
b1110011001111000 '
1"
#12000000
0"
#12050000
b111001 !
b111001 (
b11101 &
b1110100001101100 '
1"
#12100000
0"
#12150000
b1110101001100000 '
1"
#12200000
0"
#12250000
b1110110001010100 '
1"
#12300000
0"
#12350000
b1110111001001000 '
1"
#12400000
0"
#12450000
b1001111 !
b1001111 (
b11110 &
b1111000000111100 '
1"
#12500000
0"
#12550000
b1111001000110000 '
1"
#12600000
0"
#12650000
b1111010000100100 '
1"
#12700000
0"
#12750000
b1111011000011000 '
1"
#12800000
0"
#12850000
b1100111 !
b1100111 (
b11111 &
b1111100000001100 '
1"
#12900000
0"
#12950000
b1111101000000000 '
1"
#13000000
0"
#13050000
b1111101111110100 '
1"
#13100000
0"
#13150000
b1111110111101000 '
1"
#13200000
0"
#13250000
b1111111111011100 '
1"
#13300000
0"
#13350000
b10000000 !
b10000000 (
b0 &
b111010000 '
1"
#13400000
0"
#13450000
b1111000100 '
1"
#13500000
0"
#13550000
b10110111000 '
1"
#13600000
0"
#13650000
b11110101100 '
1"
#13700000
0"
#13750000
b10011001 !
b10011001 (
b1 &
b100110100000 '
1"
#13800000
0"
#13850000
b101110010100 '
1"
#13900000
0"
#13950000
b110110001000 '
1"
#14000000
0"
#14050000
b111101111100 '
1"
#14100000
0"
#14150000
b10110001 !
b10110001 (
b10 &
b1000101110000 '
1"
#14200000
0"
#14250000
b1001101100100 '
1"
#14300000
0"
#14350000
b1010101011000 '
1"
#14400000
0"
#14450000
b1011101001100 '
1"
#14500000
0"
#14550000
b11000111 !
b11000111 (
b11 &
b1100101000000 '
1"
#14600000
0"
#14650000
b1101100110100 '
1"
#14700000
0"
#14750000
b1110100101000 '
1"
#14800000
0"
#14850000
b1111100011100 '
1"
#14900000
0"
#14950000
b11011010 !
b11011010 (
b100 &
b10000100010000 '
1"
#15000000
0"
#15050000
b10001100000100 '
1"
#15100000
0"
#15150000
b10010011111000 '
1"
#15200000
0"
#15250000
b10011011101100 '
1"
#15300000
0"
#15350000
b11101010 !
b11101010 (
b101 &
b10100011100000 '
1"
#15400000
0"
#15450000
b10101011010100 '
1"
#15500000
0"
#15550000
b10110011001000 '
1"
#15600000
0"
#15650000
b10111010111100 '
1"
#15700000
0"
#15750000
b11110110 !
b11110110 (
b110 &
b11000010110000 '
1"
#15800000
0"
#15850000
b11001010100100 '
1"
#15900000
0"
#15950000
b11010010011000 '
1"
#16000000
0"
#16050000
b11011010001100 '
1"
#16100000
0"
#16150000
b11111101 !
b11111101 (
b111 &
b11100010000000 '
1"
#16200000
0"
#16250000
b11101001110100 '
1"
#16300000
0"
#16350000
b11110001101000 '
1"
#16400000
0"
#16450000
b11111001011100 '
1"
#16500000
0"
#16550000
b11111111 !
b11111111 (
b1000 &
b100000001010000 '
1"
#16600000
0"
#16650000
b100001001000100 '
1"
#16700000
0"
#16750000
b100010000111000 '
1"
#16800000
0"
#16850000
b100011000101100 '
1"
#16900000
0"
#16950000
b11111101 !
b11111101 (
b1001 &
b100100000100000 '
1"
#17000000
0"
#17050000
b100101000010100 '
1"
#17100000
0"
#17150000
b100110000001000 '
1"
#17200000
0"
#17250000
b100110111111100 '
1"
#17300000
0"
#17350000
b100111111110000 '
1"
#17400000
0"
#17450000
b11110110 !
b11110110 (
b1010 &
b101000111100100 '
1"
#17500000
0"
#17550000
b101001111011000 '
1"
#17600000
0"
#17650000
b101010111001100 '
1"
#17700000
0"
#17750000
b101011111000000 '
1"
#17800000
0"
#17850000
b11101010 !
b11101010 (
b1011 &
b101100110110100 '
1"
#17900000
0"
#17950000
b101101110101000 '
1"
#18000000
0"
#18050000
b101110110011100 '
1"
#18100000
0"
#18150000
b101111110010000 '
1"
#18200000
0"
#18250000
b11011010 !
b11011010 (
b1100 &
b110000110000100 '
1"
#18300000
0"
#18350000
b110001101111000 '
1"
#18400000
0"
#18450000
b110010101101100 '
1"
#18500000
0"
#18550000
b110011101100000 '
1"
#18600000
0"
#18650000
b11000111 !
b11000111 (
b1101 &
b110100101010100 '
1"
#18700000
0"
#18750000
b110101101001000 '
1"
#18800000
0"
#18850000
b110110100111100 '
1"
#18900000
0"
#18950000
b110111100110000 '
1"
#19000000
0"
#19050000
b10110001 !
b10110001 (
b1110 &
b111000100100100 '
1"
#19100000
0"
#19150000
b111001100011000 '
1"
#19200000
0"
#19250000
b111010100001100 '
1"
#19300000
0"
#19350000
b111011100000000 '
1"
#19400000
0"
#19450000
b10011001 !
b10011001 (
b1111 &
b111100011110100 '
1"
#19500000
0"
#19550000
b111101011101000 '
1"
#19600000
0"
#19650000
b111110011011100 '
1"
#19700000
0"
#19750000
b111111011010000 '
1"
#19800000
0"
#19850000
b10000000 !
b10000000 (
b10000 &
b1000000011000100 '
1"
#19900000
0"
#19950000
b1000001010111000 '
1"
#20000000
0"
#20050000
b1000010010101100 '
1"
#20100000
0"
#20150000
b1000011010100000 '
1"
#20200000
0"
#20250000
b1100111 !
b1100111 (
b10001 &
b1000100010010100 '
1"
#20300000
0"
#20350000
b1000101010001000 '
1"
#20400000
0"
#20450000
b1000110001111100 '
1"
#20500000
0"
#20550000
b1000111001110000 '
1"
#20600000
0"
#20650000
b1001111 !
b1001111 (
b10010 &
b1001000001100100 '
1"
#20700000
0"
#20750000
b1001001001011000 '
1"
#20800000
0"
#20850000
b1001010001001100 '
1"
#20900000
0"
#20950000
b1001011001000000 '
1"
#21000000
0"
#21050000
b111001 !
b111001 (
b10011 &
b1001100000110100 '
1"
#21100000
0"
#21150000
b1001101000101000 '
1"
#21200000
0"
#21250000
b1001110000011100 '
1"
#21300000
0"
#21350000
b1001111000010000 '
1"
#21400000
0"
#21450000
b100110 !
b100110 (
b10100 &
b1010000000000100 '
1"
#21500000
0"
#21550000
b1010000111111000 '
1"
#21600000
0"
#21650000
b1010001111101100 '
1"
#21700000
0"
#21750000
b1010010111100000 '
1"
#21800000
0"
#21850000
b1010011111010100 '
1"
#21900000
0"
#21950000
b10110 !
b10110 (
b10101 &
b1010100111001000 '
1"
#22000000
0"
#22050000
b1010101110111100 '
1"
#22100000
0"
#22150000
b1010110110110000 '
1"
#22200000
0"
#22250000
b1010111110100100 '
1"
#22300000
0"
#22350000
b1010 !
b1010 (
b10110 &
b1011000110011000 '
1"
#22400000
0"
#22450000
b1011001110001100 '
1"
#22500000
0"
#22550000
b1011010110000000 '
1"
#22600000
0"
#22650000
b1011011101110100 '
1"
#22700000
0"
#22750000
b11 !
b11 (
b10111 &
b1011100101101000 '
1"
#22800000
0"
#22850000
b1011101101011100 '
1"
#22900000
0"
#22950000
b1011110101010000 '
1"
#23000000
0"
#23050000
b1011111101000100 '
1"
#23100000
0"
#23150000
b0 !
b0 (
b11000 &
b1100000100111000 '
1"
#23200000
0"
#23250000
b1100001100101100 '
1"
#23300000
0"
#23350000
b1100010100100000 '
1"
#23400000
0"
#23450000
b1100011100010100 '
1"
#23500000
0"
#23550000
b11 !
b11 (
b11001 &
b1100100100001000 '
1"
#23600000
0"
#23650000
b1100101011111100 '
1"
#23700000
0"
#23750000
b1100110011110000 '
1"
#23800000
0"
#23850000
b1100111011100100 '
1"
#23900000
0"
#23950000
b1010 !
b1010 (
b11010 &
b1101000011011000 '
1"
#24000000
0"
#24050000
b1101001011001100 '
1"
#24100000
0"
#24150000
b1101010011000000 '
1"
#24200000
0"
#24250000
b1101011010110100 '
1"
#24300000
0"
#24350000
b10110 !
b10110 (
b11011 &
b1101100010101000 '
1"
#24400000
0"
#24450000
b1101101010011100 '
1"
#24500000
0"
#24550000
b1101110010010000 '
1"
#24600000
0"
#24650000
b1101111010000100 '
1"
#24700000
0"
#24750000
b100110 !
b100110 (
b11100 &
b1110000001111000 '
1"
#24800000
0"
#24850000
b1110001001101100 '
1"
#24900000
0"
#24950000
b1110010001100000 '
1"
#25000000
0"
#25050000
b1110011001010100 '
1"
#25100000
0"
#25150000
b111001 !
b111001 (
b11101 &
b1110100001001000 '
1"
#25200000
0"
#25250000
b1110101000111100 '
1"
#25300000
0"
#25350000
b1110110000110000 '
1"
#25400000
0"
#25450000
b1110111000100100 '
1"
#25500000
0"
#25550000
b1001111 !
b1001111 (
b11110 &
b1111000000011000 '
1"
#25600000
0"
#25650000
b1111001000001100 '
1"
#25700000
0"
#25750000
b1111010000000000 '
1"
#25800000
0"
#25850000
b1111010111110100 '
1"
#25900000
0"
#25950000
b1111011111101000 '
1"
#26000000
0"
#26050000
b1100111 !
b1100111 (
b11111 &
b1111100111011100 '
1"
#26100000
0"
#26150000
b1111101111010000 '
1"
#26200000
0"
#26250000
b1111110111000100 '
1"
#26300000
0"
#26350000
b1111111110111000 '
1"
#26400000
0"
#26450000
b10000000 !
b10000000 (
b0 &
b110101100 '
1"
#26500000
0"
#26550000
b1110100000 '
1"
#26600000
0"
#26650000
b10110010100 '
1"
#26700000
0"
#26750000
b11110001000 '
1"
#26800000
0"
#26850000
b10011001 !
b10011001 (
b1 &
b100101111100 '
1"
#26900000
0"
#26950000
b101101110000 '
1"
#27000000
0"
#27050000
b110101100100 '
1"
#27100000
0"
#27150000
b111101011000 '
1"
#27200000
0"
#27250000
b10110001 !
b10110001 (
b10 &
b1000101001100 '
1"
#27300000
0"
#27350000
b1001101000000 '
1"
#27400000
0"
#27450000
b1010100110100 '
1"
#27500000
0"
#27550000
b1011100101000 '
1"
#27600000
0"
#27650000
b11000111 !
b11000111 (
b11 &
b1100100011100 '
1"
#27700000
0"
#27750000
b1101100010000 '
1"
#27800000
0"
#27850000
b1110100000100 '
1"
#27900000
0"
#27950000
b1111011111000 '
1"
#28000000
0"
#28050000
b11011010 !
b11011010 (
b100 &
b10000011101100 '
1"
#28100000
0"
#28150000
b10001011100000 '
1"
#28200000
0"
#28250000
b10010011010100 '
1"
#28300000
0"
#28350000
b10011011001000 '
1"
#28400000
0"
#28450000
b11101010 !
b11101010 (
b101 &
b10100010111100 '
1"
#28500000
0"
#28550000
b10101010110000 '
1"
#28600000
0"
#28650000
b10110010100100 '
1"
#28700000
0"
#28750000
b10111010011000 '
1"
#28800000
0"
#28850000
b11110110 !
b11110110 (
b110 &
b11000010001100 '
1"
#28900000
0"
#28950000
b11001010000000 '
1"
#29000000
0"
#29050000
b11010001110100 '
1"
#29100000
0"
#29150000
b11011001101000 '
1"
#29200000
0"
#29250000
b11111101 !
b11111101 (
b111 &
b11100001011100 '
1"
#29300000
0"
#29350000
b11101001010000 '
1"
#29400000
0"
#29450000
b11110001000100 '
1"
#29500000
0"
#29550000
b11111000111000 '
1"
#29600000
0"
#29650000
b11111111 !
b11111111 (
b1000 &
b100000000101100 '
1"
#29700000
0"
#29750000
b100001000100000 '
1"
#29800000
0"
#29850000
b100010000010100 '
1"
#29900000
0"
#29950000
b100011000001000 '
1"
#30000000
0"
#30050000
b100011111111100 '
1"
#30100000
0"
#30150000
b11111101 !
b11111101 (
b1001 &
b100100111110000 '
1"
#30200000
0"
#30250000
b100101111100100 '
1"
#30300000
0"
#30350000
b100110111011000 '
1"
#30400000
0"
#30450000
b100111111001100 '
1"
#30500000
0"
#30550000
b11110110 !
b11110110 (
b1010 &
b101000111000000 '
1"
#30600000
0"
#30650000
b101001110110100 '
1"
#30700000
0"
#30750000
b101010110101000 '
1"
#30800000
0"
#30850000
b101011110011100 '
1"
#30900000
0"
#30950000
b11101010 !
b11101010 (
b1011 &
b101100110010000 '
1"
#31000000
0"
#31050000
b101101110000100 '
1"
#31100000
0"
#31150000
b101110101111000 '
1"
#31200000
0"
#31250000
b101111101101100 '
1"
#31300000
0"
#31350000
b11011010 !
b11011010 (
b1100 &
b110000101100000 '
1"
#31400000
0"
#31450000
b110001101010100 '
1"
#31500000
0"
#31550000
b110010101001000 '
1"
#31600000
0"
#31650000
b110011100111100 '
1"
#31700000
0"
#31750000
b11000111 !
b11000111 (
b1101 &
b110100100110000 '
1"
#31800000
0"
#31850000
b110101100100100 '
1"
#31900000
0"
#31950000
b110110100011000 '
1"
#32000000
0"
#32050000
b110111100001100 '
1"
#32100000
0"
#32150000
b10110001 !
b10110001 (
b1110 &
b111000100000000 '
1"
#32200000
0"
#32250000
b111001011110100 '
1"
#32300000
0"
#32350000
b111010011101000 '
1"
#32400000
0"
#32450000
b111011011011100 '
1"
#32500000
0"
#32550000
b10011001 !
b10011001 (
b1111 &
b111100011010000 '
1"
#32600000
0"
#32650000
b111101011000100 '
1"
#32700000
0"
#32750000
b111110010111000 '
1"
#32800000
0"
#32850000
b111111010101100 '
1"
#32900000
0"
#32950000
b10000000 !
b10000000 (
b10000 &
b1000000010100000 '
1"
#33000000
0"
#33050000
b1000001010010100 '
1"
#33100000
0"
#33150000
b1000010010001000 '
1"
#33200000
0"
#33250000
b1000011001111100 '
1"
#33300000
0"
#33350000
b1100111 !
b1100111 (
b10001 &
b1000100001110000 '
1"
#33400000
0"
#33450000
b1000101001100100 '
1"
#33500000
0"
#33550000
b1000110001011000 '
1"
#33600000
0"
#33650000
b1000111001001100 '
1"
#33700000
0"
#33750000
b1001111 !
b1001111 (
b10010 &
b1001000001000000 '
1"
#33800000
0"
#33850000
b1001001000110100 '
1"
#33900000
0"
#33950000
b1001010000101000 '
1"
#34000000
0"
#34050000
b1001011000011100 '
1"
#34100000
0"
#34150000
b111001 !
b111001 (
b10011 &
b1001100000010000 '
1"
#34200000
0"
#34250000
b1001101000000100 '
1"
#34300000
0"
#34350000
b1001101111111000 '
1"
#34400000
0"
#34450000
b1001110111101100 '
1"
#34500000
0"
#34550000
b1001111111100000 '
1"
#34600000
0"
#34650000
b100110 !
b100110 (
b10100 &
b1010000111010100 '
1"
#34700000
0"
#34750000
b1010001111001000 '
1"
#34800000
0"
#34850000
b1010010110111100 '
1"
#34900000
0"
#34950000
b1010011110110000 '
1"
#35000000
0"
#35050000
b10110 !
b10110 (
b10101 &
b1010100110100100 '
1"
#35100000
0"
#35150000
b1010101110011000 '
1"
#35200000
0"
#35250000
b1010110110001100 '
1"
#35300000
0"
#35350000
b1010111110000000 '
1"
#35400000
0"
#35450000
b1010 !
b1010 (
b10110 &
b1011000101110100 '
1"
#35500000
0"
#35550000
b1011001101101000 '
1"
#35600000
0"
#35650000
b1011010101011100 '
1"
#35700000
0"
#35750000
b1011011101010000 '
1"
#35800000
0"
#35850000
b11 !
b11 (
b10111 &
b1011100101000100 '
1"
#35900000
0"
#35950000
b1011101100111000 '
1"
#36000000
0"
#36050000
b1011110100101100 '
1"
#36100000
0"
#36150000
b1011111100100000 '
1"
#36200000
0"
#36250000
b0 !
b0 (
b11000 &
b1100000100010100 '
1"
#36300000
0"
#36350000
b1100001100001000 '
1"
#36400000
0"
#36450000
b1100010011111100 '
1"
#36500000
0"
#36550000
b1100011011110000 '
1"
#36600000
0"
#36650000
b11 !
b11 (
b11001 &
b1100100011100100 '
1"
#36700000
0"
#36750000
b1100101011011000 '
1"
#36800000
0"
#36850000
b1100110011001100 '
1"
#36900000
0"
#36950000
b1100111011000000 '
1"
#37000000
0"
#37050000
b1010 !
b1010 (
b11010 &
b1101000010110100 '
1"
#37100000
0"
#37150000
b1101001010101000 '
1"
#37200000
0"
#37250000
b1101010010011100 '
1"
#37300000
0"
#37350000
b1101011010010000 '
1"
#37400000
0"
#37450000
b10110 !
b10110 (
b11011 &
b1101100010000100 '
1"
#37500000
0"
#37550000
b1101101001111000 '
1"
#37600000
0"
#37650000
b1101110001101100 '
1"
#37700000
0"
#37750000
b1101111001100000 '
1"
#37800000
0"
#37850000
b100110 !
b100110 (
b11100 &
b1110000001010100 '
1"
#37900000
0"
#37950000
b1110001001001000 '
1"
#38000000
0"
#38050000
b1110010000111100 '
1"
#38100000
0"
#38150000
b1110011000110000 '
1"
#38200000
0"
#38250000
b111001 !
b111001 (
b11101 &
b1110100000100100 '
1"
#38300000
0"
#38350000
b1110101000011000 '
1"
#38400000
0"
#38450000
b1110110000001100 '
1"
#38500000
0"
#38550000
b1110111000000000 '
1"
#38600000
0"
#38650000
b1110111111110100 '
1"
#38700000
0"
#38750000
b1001111 !
b1001111 (
b11110 &
b1111000111101000 '
1"
#38800000
0"
#38850000
b1111001111011100 '
1"
#38900000
0"
#38950000
b1111010111010000 '
1"
#39000000
0"
#39050000
b1111011111000100 '
1"
#39100000
0"
#39150000
b1100111 !
b1100111 (
b11111 &
b1111100110111000 '
1"
#39200000
0"
#39250000
b1111101110101100 '
1"
#39300000
0"
#39350000
b1111110110100000 '
1"
#39400000
0"
#39450000
b1111111110010100 '
1"
#39500000
0"
#39550000
b10000000 !
b10000000 (
b0 &
b110001000 '
1"
#39600000
0"
#39650000
b1101111100 '
1"
#39700000
0"
#39750000
b10101110000 '
1"
#39800000
0"
#39850000
b11101100100 '
1"
#39900000
0"
#39950000
b10011001 !
b10011001 (
b1 &
b100101011000 '
1"
#40000000
0"
#40050000
b101101001100 '
1"
#40100000
0"
#40150000
b110101000000 '
1"
#40200000
0"
#40250000
b111100110100 '
1"
#40300000
0"
#40350000
b10110001 !
b10110001 (
b10 &
b1000100101000 '
1"
#40400000
0"
#40450000
b1001100011100 '
1"
#40500000
0"
#40550000
b1010100010000 '
1"
#40600000
0"
#40650000
b1011100000100 '
1"
#40700000
0"
#40750000
b11000111 !
b11000111 (
b11 &
b1100011111000 '
1"
#40800000
0"
#40850000
b1101011101100 '
1"
#40900000
0"
#40950000
b1110011100000 '
1"
#41000000
0"
#41050000
b1111011010100 '
1"
#41100000
0"
#41150000
b11011010 !
b11011010 (
b100 &
b10000011001000 '
1"
#41200000
0"
#41250000
b10001010111100 '
1"
#41300000
0"
#41350000
b10010010110000 '
1"
#41400000
0"
#41450000
b10011010100100 '
1"
#41500000
0"
#41550000
b11101010 !
b11101010 (
b101 &
b10100010011000 '
1"
#41600000
0"
#41650000
b10101010001100 '
1"
#41700000
0"
#41750000
b10110010000000 '
1"
#41800000
0"
#41850000
b10111001110100 '
1"
#41900000
0"
#41950000
b11110110 !
b11110110 (
b110 &
b11000001101000 '
1"
#42000000
0"
#42050000
b11001001011100 '
1"
#42100000
0"
#42150000
b11010001010000 '
1"
#42200000
0"
#42250000
b11011001000100 '
1"
#42300000
0"
#42350000
b11111101 !
b11111101 (
b111 &
b11100000111000 '
1"
#42400000
0"
#42450000
b11101000101100 '
1"
#42500000
0"
#42550000
b11110000100000 '
1"
#42600000
0"
#42650000
b11111000010100 '
1"
#42700000
0"
