dbn0301/Verilog Files/debouncer.v
`timescale 1ns / 1ps

module debouncer #(
    parameter DEBOUNCE_LIMIT = 16'd2000
)(
    input  wire clk,          // High-speed system clock (e.g., 10 MHz)
    input  wire rst_n,        // Active-low reset
    input  wire button_in,    // The messy, bouncing physical button

    output reg  button_out    // The clean, debounced digital output
);

    //------------------------------------------------------------------------
    // 1. ASYNCHRONOUS SYNCHRONIZER
    //------------------------------------------------------------------------
    // A physical button press is asynchronous. We MUST align it to our clock.
    reg sync_1, sync_2;

    always @(posedge clk or negedge rst_n) begin
        if (!rst_n) begin
            sync_1 <= 1'b0;
            sync_2 <= 1'b0;
        end else begin
            sync_1 <= button_in;
            sync_2 <= sync_1;
        end
    end

    //------------------------------------------------------------------------
    // 2. THE STABILITY COUNTER
    //------------------------------------------------------------------------
    reg [15:0] counter;

    always @(posedge clk or negedge rst_n) begin
        if (!rst_n) begin
            counter    <= 16'd0;
            button_out <= 1'b0;
        end else begin
            // If the synchronized input matches our current output, 
            // the signal is stable. Do nothing and keep the counter at 0.
            if (sync_2 == button_out) begin
                counter <= 16'd0;
            end 
            // If they don't match, a transition (or a bounce) is happening!
            else begin
                counter <= counter + 16'd1;
                
                // If the signal has remained stable for the entire DEBOUNCE_LIMIT...
                if (counter >= DEBOUNCE_LIMIT) begin
                    button_out <= sync_2; // Accept the new state!
                    counter    <= 16'd0;  // Reset counter
                end
            end
        end
    end

endmodule

dbn0301/Verilog Files/tb_debouncer.v
`timescale 1ns / 1ps

module tb_debouncer;

    // Inputs
    reg clk;
    reg rst_n;
    reg button_in;

    // Outputs
    wire button_out;

    // Instantiate the Unit Under Test (UUT)
    // We override the parameter to '50' for faster simulation viewing
    debouncer #(.DEBOUNCE_LIMIT(16'd50)) uut (
        .clk(clk), 
        .rst_n(rst_n), 
        .button_in(button_in), 
        .button_out(button_out)
    );

    // Generate 10 MHz System Clock (100ns period)
    initial begin
        clk = 0;
        forever #50 clk = ~clk;
    end

    // TASK: Simulate a terrible, cheap mechanical button bouncing
    task mechanical_press;
        begin
            $display("Time: %0t ns | Physical Button Pressed! (Bouncing starts)", $time);
            button_in = 1; #120;  // Initial contact
            button_in = 0; #80;   // Bounces off
            button_in = 1; #200;  // Hits again
            button_in = 0; #350;  // Bounces off harder
            button_in = 1; #90;   // Hits again
            button_in = 0; #40;   // Micro bounce
            button_in = 1;        // Finally settles and stays connected
        end
    endtask

    task mechanical_release;
        begin
            $display("Time: %0t ns | Physical Button Released! (Bouncing starts)", $time);
            button_in = 0; #150;  
            button_in = 1; #90;   
            button_in = 0; #210;  
            button_in = 1; #50;   
            button_in = 0;        // Finally settles open
        end
    endtask

    // Main Test Stimulus
    initial begin
        // Setup GTKWave Output
        $dumpfile("debounce_sim.vcd");
        $dumpvars(0, tb_debouncer);

        // Initialize Inputs
        rst_n = 0;
        button_in = 0;

        // Release Reset
        #200;
        rst_n = 1;

        // 1. Simulate a messy button press
        #500;
        mechanical_press();

        // Wait for the debouncer to recognize the solid signal
        #10000;

        // 2. Simulate a messy button release
        mechanical_release();

        #10000;
        $display("--- Simulation Complete ---");
        $finish;
    end

endmodule

dbn0301/eSim Test Circuit Project Files/debounce_sim.vcd
$date
	Sun Jun 21 09:59:32 2026
$end
$version
	Icarus Verilog
$end
$timescale
	1ps
$end
$scope module tb_debouncer $end
$var wire 1 ! button_out $end
$var reg 1 " button_in $end
$var reg 1 # clk $end
$var reg 1 $ rst_n $end
$scope module uut $end
$var wire 1 " button_in $end
$var wire 1 # clk $end
$var wire 1 $ rst_n $end
$var parameter 16 % DEBOUNCE_LIMIT $end
$var reg 1 ! button_out $end
$var reg 16 & counter [15:0] $end
$var reg 1 ' sync_1 $end
$var reg 1 ( sync_2 $end
$upscope $end
$scope task mechanical_press $end
$upscope $end
$scope task mechanical_release $end
$upscope $end
$upscope $end
$enddefinitions $end
$comment Show the parameter values. $end
$dumpall
b110010 %
$end
#0
$dumpvars
0(
0'
b0 &
0$
0#
0"
0!
$end
#50000
1#
#100000
0#
#150000
1#
#200000
0#
1$
#250000
1#
#300000
0#
#350000
1#
#400000
0#
#450000
1#
#500000
0#
#550000
1#
#600000
0#
#650000
1#
#700000
0#
1"
#750000
1'
1#
#800000
0#
#820000
0"
#850000
1(
0'
1#
#900000
0#
1"
#950000
0(
1'
b1 &
1#
#1000000
0#
#1050000
b0 &
1(
1#
#1100000
0#
0"
#1150000
0'
b1 &
1#
#1200000
0#
#1250000
b10 &
0(
1#
#1300000
0#
#1350000
b0 &
1#
#1400000
0#
#1450000
1'
1#
1"
#1500000
0#
#1540000
0"
#1550000
1(
0'
1#
#1580000
1"
#1600000
0#
#1650000
b1 &
0(
1'
1#
#1700000
0#
#1750000
1(
b0 &
1#
#1800000
0#
#1850000
b1 &
1#
#1900000
0#
#1950000
b10 &
1#
#2000000
0#
#2050000
b11 &
1#
#2100000
0#
#2150000
b100 &
1#
#2200000
0#
#2250000
b101 &
1#
#2300000
0#
#2350000
b110 &
1#
#2400000
0#
#2450000
b111 &
1#
#2500000
0#
#2550000
b1000 &
1#
#2600000
0#
#2650000
b1001 &
1#
#2700000
0#
#2750000
b1010 &
1#
#2800000
0#
#2850000
b1011 &
1#
#2900000
0#
#2950000
b1100 &
1#
#3000000
0#
#3050000
b1101 &
1#
#3100000
0#
#3150000
b1110 &
1#
#3200000
0#
#3250000
b1111 &
1#
#3300000
0#
#3350000
b10000 &
1#
#3400000
0#
#3450000
b10001 &
1#
#3500000
0#
#3550000
b10010 &
1#
#3600000
0#
#3650000
b10011 &
1#
#3700000
0#
#3750000
b10100 &
1#
#3800000
0#
#3850000
b10101 &
1#
#3900000
0#
#3950000
b10110 &
1#
#4000000
0#
#4050000
b10111 &
1#
#4100000
0#
#4150000
b11000 &
1#
#4200000
0#
#4250000
b11001 &
1#
#4300000
0#
#4350000
b11010 &
1#
#4400000
0#
#4450000
b11011 &
1#
#4500000
0#
#4550000
b11100 &
1#
#4600000
0#
#4650000
b11101 &
1#
#4700000
0#
#4750000
b11110 &
1#
#4800000
0#
#4850000
b11111 &
1#
#4900000
0#
#4950000
b100000 &
1#
#5000000
0#
#5050000
b100001 &
1#
#5100000
0#
#5150000
b100010 &
1#
#5200000
0#
#5250000
b100011 &
1#
#5300000
0#
#5350000
b100100 &
1#
#5400000
0#
#5450000
b100101 &
1#
#5500000
0#
#5550000
b100110 &
1#
#5600000
0#
#5650000
b100111 &
1#
#5700000
0#
#5750000
b101000 &
1#
#5800000
0#
#5850000
b101001 &
1#
#5900000
0#
#5950000
b101010 &
1#
#6000000
0#
#6050000
b101011 &
1#
#6100000
0#
#6150000
b101100 &
1#
#6200000
0#
#6250000
b101101 &
1#
#6300000
0#
#6350000
b101110 &
1#
#6400000
0#
#6450000
b101111 &
1#
#6500000
0#
#6550000
b110000 &
1#
#6600000
0#
#6650000
b110001 &
1#
#6700000
0#
#6750000
b110010 &
1#
#6800000
0#
#6850000
1!
b0 &
1#
