ddbcd1113/Verilog Files/double_dabble.v

module double_dabble (
    input  wire        clk,      // System clock
    input  wire        rst_n,    // Active-low asynchronous reset
    input  wire        start,    // Pulse high for 1 clock cycle to begin
    input  wire [7:0]  bin_in,   // 8-bit binary input (Max 255)
    output reg  [11:0] bcd_out,  // 12-bit BCD output (Hundreds, Tens, Ones)
    output reg         done      // Goes high when conversion is complete
);

    // FSM State Encoding
    localparam IDLE  = 2'b00;
    localparam ADD3  = 2'b01;
    localparam SHIFT = 2'b10;
    localparam DONE  = 2'b11;

    reg [1:0]  state;
    reg [19:0] shift_reg;  // 20-bit register: [19:8] is BCD, [7:0] is Binary
    reg [3:0]  shift_cnt;  // Tracks the 8 required shifts

    // Combinational evaluation signals for the "Dabble" (Add 3) step
    wire [3:0] nibble1 = shift_reg[11:8];
    wire [3:0] nibble2 = shift_reg[15:12];
    wire [3:0] nibble3 = shift_reg[19:16];

    always @(posedge clk or negedge rst_n) begin
        if (!rst_n) begin
            state     <= IDLE;
            shift_reg <= 20'd0;
            shift_cnt <= 4'd0;
            bcd_out   <= 12'd0;
            done      <= 1'b0;
        end else begin
            case (state)
                IDLE: begin
                    done <= 1'b0;
                    if (start) begin
                        // Load the binary input into the lower 8 bits, clear upper 12 bits
                        shift_reg <= {12'd0, bin_in};
                        shift_cnt <= 4'd0;
                        state     <= ADD3;
                    end
                end

                ADD3: begin
                    // Check each BCD column. If >= 5, add 3.
                    // This is done concurrently using concatenation to be perfectly safe in synthesis.
                    shift_reg[19:8] <= {
                        (nibble3 >= 5) ? (nibble3 + 4'd3) : nibble3,
                        (nibble2 >= 5) ? (nibble2 + 4'd3) : nibble2,
                        (nibble1 >= 5) ? (nibble1 + 4'd3) : nibble1
                    };
                    state <= SHIFT;
                end

                SHIFT: begin
                    // Shift the entire 20-bit register left by 1
                    shift_reg <= shift_reg << 1;
                    shift_cnt <= shift_cnt + 4'd1;
                    
                    // If we have shifted 8 times, we are done
                    if (shift_cnt == 4'd7) begin 
                        state <= DONE;
                    end else begin
                        state <= ADD3;
                    end
                end

                DONE: begin
                    // Latch the final BCD value to the output port
                    bcd_out <= shift_reg[19:8];
                    done    <= 1'b1;
                    state   <= IDLE;
                end
                
                default: state <= IDLE;
            endcase
        end
    end

endmodule

ddbcd1113/Verilog Files/double_dabble_tb.v
`timescale 1ns / 1ps

module double_dabble_tb;

    // Inputs
    reg clk;
    reg rst_n;
    reg start;
    reg [7:0] bin_in;

    // Outputs
    wire [11:0] bcd_out;
    wire done;

    // Instantiate the Unit Under Test (UUT)
    double_dabble uut (
        .clk(clk),
        .rst_n(rst_n),
        .start(start),
        .bin_in(bin_in),
        .bcd_out(bcd_out),
        .done(done)
    );

    // Clock generation (10ns period -> 100MHz)
    initial begin
        clk = 0;
        forever #5 clk = ~clk;
    end

    // Test Stimulus
    initial begin
        // 1. Setup VCD file dumping for GTKWave visualization
        $dumpfile("double_dabble.vcd");
        $dumpvars(0, double_dabble_tb);

        // 2. Initialize Inputs & Apply Reset
        rst_n  = 0;
        start  = 0;
        bin_in = 0;

        #20;
        rst_n = 1; // Release reset
        #15;       // Offset from clock edge to avoid race conditions

        // --- TEST CASE 1: Maximum 8-bit value (255) ---
        $display("--- Starting Test Case 1 ---");
        bin_in = 8'd255;
        start  = 1;
        #10;
        start  = 0; // Pulse start for exactly 1 clock cycle

        wait(done == 1'b1); // Block until FSM asserts done
        #10;
        // Print result in Hex (%x) so BCD prints visually as decimal numbers
        $display("Time: %0t | Binary: %d | BCD Output: %x (Expected: 255)", $time, bin_in, bcd_out);

        // --- TEST CASE 2: Random mid-range value (123) ---
        #30;
        $display("--- Starting Test Case 2 ---");
        bin_in = 8'd123;
        start  = 1;
        #10;
        start  = 0;

        wait(done == 1'b1);
        #10;
        $display("Time: %0t | Binary: %d | BCD Output: %x (Expected: 123)", $time, bin_in, bcd_out);

        // --- TEST CASE 3: Single digit value (9) ---
        #30;
        $display("--- Starting Test Case 3 ---");
        bin_in = 8'd9;
        start  = 1;
        #10;
        start  = 0;

        wait(done == 1'b1);
        #10;
        $display("Time: %0t | Binary: %d | BCD Output: %x (Expected: 009)", $time, bin_in, bcd_out);

        // 3. End simulation gracefully
        #50;
        $display("--- Simulation Complete ---");
        $finish;
    end

endmodule

ddbcd1113/eSim Test Circuit Project Files/double_dabble.vcd
$date
	Mon Jun 01 15:50:12 2026
$end
$version
	Icarus Verilog
$end
$timescale
	1ps
$end
$scope module double_dabble_tb $end
$var wire 1 ! done $end
$var wire 12 " bcd_out [11:0] $end
$var reg 8 # bin_in [7:0] $end
$var reg 1 $ clk $end
$var reg 1 % rst_n $end
$var reg 1 & start $end
$scope module uut $end
$var wire 8 ' bin_in [7:0] $end
$var wire 1 $ clk $end
$var wire 1 % rst_n $end
$var wire 1 & start $end
$var wire 4 ( nibble3 [3:0] $end
$var wire 4 ) nibble2 [3:0] $end
$var wire 4 * nibble1 [3:0] $end
$var parameter 2 + ADD3 $end
$var parameter 2 , DONE $end
$var parameter 2 - IDLE $end
$var parameter 2 . SHIFT $end
$var reg 12 / bcd_out [11:0] $end
$var reg 1 ! done $end
$var reg 4 0 shift_cnt [3:0] $end
$var reg 20 1 shift_reg [19:0] $end
$var reg 2 2 state [1:0] $end
$upscope $end
$upscope $end
$enddefinitions $end
$comment Show the parameter values. $end
$dumpall
b10 .
b0 -
b11 ,
b1 +
$end
#0
$dumpvars
b0 2
b0 1
b0 0
b0 /
b0 *
b0 )
b0 (
b0 '
0&
0%
0$
b0 #
b0 "
0!
$end
#5000
1$
#10000
0$
#15000
1$
#20000
0$
1%
#25000
1$
#30000
0$
#35000
b1 2
b11111111 1
1$
1&
b11111111 #
b11111111 '
#40000
0$
#45000
b10 2
1$
0&
#50000
0$
#55000
b1 *
b1 2
b1 0
b111111110 1
1$
#60000
0$
#65000
b10 2
1$
#70000
0$
#75000
b11 *
b1 2
b10 0
b1111111100 1
1$
#80000
0$
#85000
b10 2
1$
#90000
0$
#95000
b111 *
b1 2
b11 0
b11111111000 1
1$
#100000
0$
#105000
b1010 *
b10 2
b101011111000 1
1$
#110000
0$
#115000
b101 *
b1 )
b1 2
b100 0
b1010111110000 1
1$
#120000
0$
#125000
b1000 *
b10 2
b1100011110000 1
1$
#130000
0$
#135000
b1 *
b11 )
b1 2
b101 0
b11000111100000 1
1$
#140000
0$
#145000
b10 2
1$
#150000
0$
#155000
b11 *
b110 )
b1 2
b110 0
b110001111000000 1
1$
#160000
0$
#165000
b1001 )
b10 2
b1001001111000000 1
1$
#170000
0$
#175000
b111 *
b10 )
b1 (
b1 2
b111 0
b10010011110000000 1
1$
#180000
0$
#185000
b1010 *
b10 2
b10010101010000000 1
1$
#190000
0$
#195000
b101 *
b101 )
b10 (
b11 2
b1000 0
b100101010100000000 1
1$
#200000
0$
#205000
b0 2
1!
b1001010101 "
b1001010101 /
1$
#210000
0$
#215000
0!
1$
#220000
0$
#225000
1$
#230000
0$
#235000
1$
#240000
0$
#245000
b0 *
b0 )
b0 (
b1 2
b0 0
b1111011 1
1$
1&
b1111011 #
b1111011 '
#250000
0$
#255000
b10 2
1$
0&
#260000
0$
#265000
b1 2
b1 0
b11110110 1
1$
#270000
0$
#275000
b10 2
1$
#280000
0$
#285000
b1 *
b1 2
b10 0
b111101100 1
1$
#290000
0$
#295000
b10 2
1$
#300000
0$
#305000
b11 *
b1 2
b11 0
b1111011000 1
1$
#310000
0$
#315000
b10 2
1$
#320000
0$
#325000
b111 *
b1 2
b100 0
b11110110000 1
1$
#330000
0$
#335000
b1010 *
b10 2
b101010110000 1
1$
#340000
0$
#345000
b101 *
b1 )
b1 2
b101 0
b1010101100000 1
1$
#350000
0$
#355000
b1000 *
b10 2
b1100001100000 1
1$
#360000
0$
#365000
b0 *
b11 )
b1 2
b110 0
b11000011000000 1
1$
#370000
0$
#375000
b10 2
1$
#380000
0$
#385000
b1 *
b110 )
b1 2
b111 0
b110000110000000 1
1$
#390000
0$
#395000
b1001 )
b10 2
b1001000110000000 1
1$
#400000
0$
#405000
b11 *
b10 )
b1 (
b11 2
b1000 0
b10010001100000000 1
1$
#410000
0$
#415000
b0 2
1!
b100100011 "
b100100011 /
1$
#420000
0$
#425000
0!
1$
#430000
0$
#435000
1$
#440000
0$
#445000
1$
#450000
0$
#455000
b0 *
b0 )
b0 (
b1 2
b0 0
b1001 1
1$
1&
b1001 #
b1001 '
#460000
0$
#465000
b10 2
1$
0&
#470000
0$
#475000
b1 2
b1 0
b10010 1
1$
#480000
0$
#485000
b10 2
1$
#490000
0$
#495000
b1 2
b10 0
b100100 1
1$
#500000
0$
#505000
b10 2
1$
#510000
0$
#515000
b1 2
b11 0
b1001000 1
1$
#520000
0$
#525000
b10 2
1$
#530000
0$
#535000
b1 2
b100 0
b10010000 1
1$
#540000
0$
#545000
b10 2
1$
#550000
0$
#555000
b1 *
b1 2
b101 0
b100100000 1
1$
#560000
0$
#565000
b10 2
1$
#570000
0$
#575000
b10 *
b1 2
b110 0
b1001000000 1
1$
#580000
0$
#585000
b10 2
1$
#590000
0$
#595000
b100 *
b1 2
b111 0
b10010000000 1
1$
#600000
0$
#605000
b10 2
1$
#610000
0$
#615000
b1001 *
b11 2
b1000 0
b100100000000 1
1$
#620000
0$
#625000
b0 2
1!
b1001 "
b1001 /
1$
#630000
0$
#635000
0!
1$
