dinteg1008/Verilog Files/integrator.v
`timescale 1ns / 1ps

module integrator (
    input  wire        clk,        // System clock
    input  wire        rst_n,      // Active-low reset
    input  wire [7:0]  data_in,    // 8-bit ADC input (analog waveform)
    
    output reg  [7:0]  data_out    // 8-bit DAC output (the integral)
);

    // Calculate the scaled integration step
    // We divide by 32 (>> 5) to slow down the digital charging/discharging,
    // perfectly mimicking the Time Constant (RC) of an analog capacitor.
    wire [7:0] step = (data_in >= 8'd128) ? ((data_in - 8'd128) >> 5) : ((8'd128 - data_in) >> 5);

    always @(posedge clk or negedge rst_n) begin
        if (!rst_n) begin
            data_out <= 8'd128;   // Default to mid-rail (2.5V)
        end else begin
            // Execute Discrete Integration: y[n] = y[n-1] + x[n]
            if (data_in >= 8'd128) begin
                // Positive Integration (Charging Capacitor)
                // Use 9-bit math to prevent invisible overflow wrapping
                if ({1'b0, data_out} + {1'b0, step} > 9'd255) 
                    data_out <= 8'd255; 
                else 
                    data_out <= data_out + step;
                    
            end else begin
                // Negative Integration (Discharging Capacitor)
                if (data_out < step) 
                    data_out <= 8'd0; 
                else 
                    data_out <= data_out - step;
            end
        end
    end

endmodule

dinteg1008/Verilog Files/square_gen.v
`timescale 1ns / 1ps

module square_gen (
    input  wire       clk,
    input  wire       rst_n,
    output reg  [7:0] wave_out
);
    
    reg [6:0] counter; // 7-bit counter (0 to 127)

    always @(posedge clk or negedge rst_n) begin
        if (!rst_n) begin
            counter  <= 7'd0;
            wave_out <= 8'd128;
        end else begin
            counter <= counter + 1'b1;
            
            // Toggle output between High and Low every 64 clock cycles
            if (counter < 7'd64) begin
                wave_out <= 8'd192; // Positive amplitude (charges integrator)
            end else begin
                wave_out <= 8'd64;  // Negative amplitude (discharges integrator)
            end
        end
    end
    
endmodule

dinteg1008/Verilog Files/tb_integrator.v
`timescale 1ns / 1ps

module tb_integrator;

    reg clk;
    reg rst_n;
    
    wire [7:0] square_wave; // Output from generator, input to integrator
    wire [7:0] triangle_wave; // Output from integrator

    // Instantiate the Square Wave Generator
    square_gen gen (
        .clk(clk),
        .rst_n(rst_n),
        .wave_out(square_wave)
    );

    // Instantiate the Digital Integrator
    integrator uut (
        .clk(clk),
        .rst_n(rst_n),
        .data_in(square_wave),
        .data_out(triangle_wave)
    );

    // 10 MHz System Clock (100ns period)
    initial begin
        clk = 0;
        forever #50 clk = ~clk; 
    end

    initial begin
        // Setup GTKWave dump
        $dumpfile("integrator_sim.vcd");
        $dumpvars(0, tb_integrator);

        // Initialize reset
        rst_n = 0;
        
        // Hold reset for a couple of clock cycles
        #200;
        rst_n = 1;

        // The square wave takes 12.8 microseconds for a full period.
        // We will run the simulation for 50 microseconds to see a few full waves.
        #50000;
        
        $display("--- Digital Simulation Complete ---");
        $finish;
    end

endmodule

dinteg1008/eSim Test Circuit Project Files/integrator_sim.vcd
$date
	Sun Jun 28 21:19:11 2026
$end
$version
	Icarus Verilog
$end
$timescale
	1ps
$end
$scope module tb_integrator $end
$var wire 8 ! triangle_wave [7:0] $end
$var wire 8 " square_wave [7:0] $end
$var reg 1 # clk $end
$var reg 1 $ rst_n $end
$scope module gen $end
$var wire 1 # clk $end
$var wire 1 $ rst_n $end
$var reg 7 % counter [6:0] $end
$var reg 8 & wave_out [7:0] $end
$upscope $end
$scope module uut $end
$var wire 1 # clk $end
$var wire 8 ' data_in [7:0] $end
$var wire 1 $ rst_n $end
$var wire 8 ( step [7:0] $end
$var reg 8 ) data_out [7:0] $end
$upscope $end
$upscope $end
$enddefinitions $end
$comment Show the parameter values. $end
$dumpall
$end
#0
$dumpvars
b10000000 )
b0 (
b10000000 '
b10000000 &
b0 %
0$
0#
b10000000 "
b10000000 !
$end
#50000
1#
#100000
0#
#150000
1#
#200000
0#
1$
#250000
b10 (
b11000000 "
b11000000 &
b11000000 '
b1 %
1#
#300000
0#
#350000
b10 %
b10000010 !
b10000010 )
1#
#400000
0#
#450000
b10000100 !
b10000100 )
b11 %
1#
#500000
0#
#550000
b100 %
b10000110 !
b10000110 )
1#
#600000
0#
#650000
b10001000 !
b10001000 )
b101 %
1#
#700000
0#
#750000
b110 %
b10001010 !
b10001010 )
1#
#800000
0#
#850000
b10001100 !
b10001100 )
b111 %
1#
#900000
0#
#950000
b1000 %
b10001110 !
b10001110 )
1#
#1000000
0#
#1050000
b10010000 !
b10010000 )
b1001 %
1#
#1100000
0#
#1150000
b1010 %
b10010010 !
b10010010 )
1#
#1200000
0#
#1250000
b10010100 !
b10010100 )
b1011 %
1#
#1300000
0#
#1350000
b1100 %
b10010110 !
b10010110 )
1#
#1400000
0#
#1450000
b10011000 !
b10011000 )
b1101 %
1#
#1500000
0#
#1550000
b1110 %
b10011010 !
b10011010 )
1#
#1600000
0#
#1650000
b10011100 !
b10011100 )
b1111 %
1#
#1700000
0#
#1750000
b10000 %
b10011110 !
b10011110 )
1#
#1800000
0#
#1850000
b10100000 !
b10100000 )
b10001 %
1#
#1900000
0#
#1950000
b10010 %
b10100010 !
b10100010 )
1#
#2000000
0#
#2050000
b10100100 !
b10100100 )
b10011 %
1#
#2100000
0#
#2150000
b10100 %
b10100110 !
b10100110 )
1#
#2200000
0#
#2250000
b10101000 !
b10101000 )
b10101 %
1#
#2300000
0#
#2350000
b10110 %
b10101010 !
b10101010 )
1#
#2400000
0#
#2450000
b10101100 !
b10101100 )
b10111 %
1#
#2500000
0#
#2550000
b11000 %
b10101110 !
b10101110 )
1#
#2600000
0#
#2650000
b10110000 !
b10110000 )
b11001 %
1#
#2700000
0#
#2750000
b11010 %
b10110010 !
b10110010 )
1#
#2800000
0#
#2850000
b10110100 !
b10110100 )
b11011 %
1#
#2900000
0#
#2950000
b11100 %
b10110110 !
b10110110 )
1#
#3000000
0#
#3050000
b10111000 !
b10111000 )
b11101 %
1#
#3100000
0#
#3150000
b11110 %
b10111010 !
b10111010 )
1#
#3200000
0#
#3250000
b10111100 !
b10111100 )
b11111 %
1#
#3300000
0#
#3350000
b100000 %
b10111110 !
b10111110 )
1#
#3400000
0#
#3450000
b11000000 !
b11000000 )
b100001 %
1#
#3500000
0#
#3550000
b100010 %
b11000010 !
b11000010 )
1#
#3600000
0#
#3650000
b11000100 !
b11000100 )
b100011 %
1#
#3700000
0#
#3750000
b100100 %
b11000110 !
b11000110 )
1#
#3800000
0#
#3850000
b11001000 !
b11001000 )
b100101 %
1#
#3900000
0#
#3950000
b100110 %
b11001010 !
b11001010 )
1#
#4000000
0#
#4050000
b11001100 !
b11001100 )
b100111 %
1#
#4100000
0#
#4150000
b101000 %
b11001110 !
b11001110 )
1#
#4200000
0#
#4250000
b11010000 !
b11010000 )
b101001 %
1#
#4300000
0#
#4350000
b101010 %
b11010010 !
b11010010 )
1#
#4400000
0#
#4450000
b11010100 !
b11010100 )
b101011 %
1#
#4500000
0#
#4550000
b101100 %
b11010110 !
b11010110 )
1#
#4600000
0#
#4650000
b11011000 !
b11011000 )
b101101 %
1#
#4700000
0#
#4750000
b101110 %
b11011010 !
b11011010 )
1#
#4800000
0#
#4850000
b11011100 !
b11011100 )
b101111 %
1#
#4900000
0#
#4950000
b110000 %
b11011110 !
b11011110 )
1#
#5000000
0#
#5050000
b11100000 !
b11100000 )
b110001 %
1#
#5100000
0#
#5150000
b110010 %
b11100010 !
b11100010 )
1#
#5200000
0#
#5250000
b11100100 !
b11100100 )
b110011 %
1#
#5300000
0#
#5350000
b110100 %
b11100110 !
b11100110 )
1#
#5400000
0#
#5450000
b11101000 !
b11101000 )
b110101 %
1#
#5500000
0#
#5550000
b110110 %
b11101010 !
b11101010 )
1#
#5600000
0#
#5650000
b11101100 !
b11101100 )
b110111 %
1#
#5700000
0#
#5750000
b111000 %
b11101110 !
b11101110 )
1#
#5800000
0#
#5850000
b11110000 !
b11110000 )
b111001 %
1#
#5900000
0#
#5950000
b111010 %
b11110010 !
b11110010 )
1#
#6000000
0#
#6050000
b11110100 !
b11110100 )
b111011 %
1#
#6100000
0#
#6150000
b111100 %
b11110110 !
b11110110 )
1#
#6200000
0#
#6250000
b11111000 !
b11111000 )
b111101 %
1#
#6300000
0#
#6350000
b111110 %
b11111010 !
b11111010 )
1#
#6400000
0#
#6450000
b11111100 !
b11111100 )
b111111 %
1#
#6500000
0#
#6550000
b1000000 %
b11111110 !
b11111110 )
1#
#6600000
0#
#6650000
b0 !
b0 )
b1000000 "
b1000000 &
b1000000 '
b1000001 %
1#
#6700000
0#
#6750000
b1000010 %
1#
#6800000
0#
#6850000
b1000011 %
1#
#6900000
0#
#6950000
b1000100 %
1#
#7000000
0#
#7050000
b1000101 %
1#
#7100000
0#
#7150000
b1000110 %
1#
#7200000
0#
#7250000
b1000111 %
1#
#7300000
0#
#7350000
b1001000 %
1#
#7400000
0#
#7450000
b1001001 %
1#
#7500000
0#
#7550000
b1001010 %
1#
#7600000
0#
#7650000
b1001011 %
1#
#7700000
0#
#7750000
b1001100 %
1#
#7800000
0#
#7850000
b1001101 %
1#
#7900000
0#
#7950000
b1001110 %
1#
#8000000
0#
#8050000
b1001111 %
1#
#8100000
0#
#8150000
b1010000 %
1#
#8200000
0#
#8250000
b1010001 %
1#
#8300000
0#
#8350000
b1010010 %
1#
#8400000
0#
#8450000
b1010011 %
1#
#8500000
0#
#8550000
b1010100 %
1#
#8600000
0#
#8650000
b1010101 %
1#
#8700000
0#
#8750000
b1010110 %
1#
#8800000
0#
#8850000
b1010111 %
1#
#8900000
0#
#8950000
b1011000 %
1#
#9000000
0#
#9050000
b1011001 %
1#
#9100000
0#
#9150000
b1011010 %
1#
#9200000
0#
#9250000
b1011011 %
1#
#9300000
0#
#9350000
b1011100 %
1#
#9400000
0#
#9450000
b1011101 %
1#
#9500000
0#
#9550000
b1011110 %
1#
#9600000
0#
#9650000
b1011111 %
1#
#9700000
0#
#9750000
b1100000 %
1#
#9800000
0#
#9850000
b1100001 %
1#
#9900000
0#
#9950000
b1100010 %
1#
#10000000
0#
#10050000
b1100011 %
1#
#10100000
0#
#10150000
b1100100 %
1#
#10200000
0#
#10250000
b1100101 %
1#
#10300000
0#
#10350000
b1100110 %
1#
#10400000
0#
#10450000
b1100111 %
1#
#10500000
0#
#10550000
b1101000 %
1#
#10600000
0#
#10650000
b1101001 %
1#
#10700000
0#
#10750000
b1101010 %
1#
#10800000
0#
#10850000
b1101011 %
1#
#10900000
0#
#10950000
b1101100 %
1#
#11000000
0#
#11050000
b1101101 %
1#
#11100000
0#
#11150000
b1101110 %
1#
#11200000
0#
#11250000
b1101111 %
1#
#11300000
0#
#11350000
b1110000 %
1#
#11400000
0#
#11450000
b1110001 %
1#
#11500000
0#
#11550000
b1110010 %
1#
#11600000
0#
#11650000
b1110011 %
1#
#11700000
0#
#11750000
b1110100 %
1#
#11800000
0#
#11850000
b1110101 %
1#
#11900000
0#
#11950000
b1110110 %
1#
#12000000
0#
#12050000
b1110111 %
1#
#12100000
0#
#12150000
b1111000 %
1#
#12200000
0#
#12250000
b1111001 %
1#
#12300000
0#
#12350000
b1111010 %
1#
#12400000
0#
#12450000
b1111011 %
1#
#12500000
0#
#12550000
b1111100 %
1#
#12600000
0#
#12650000
b1111101 %
1#
#12700000
0#
#12750000
b1111110 %
1#
#12800000
0#
#12850000
b1111111 %
1#
#12900000
0#
#12950000
b0 %
1#
#13000000
0#
#13050000
b11000000 "
b11000000 &
b11000000 '
b1 %
1#
#13100000
0#
#13150000
b10 %
b10 !
b10 )
1#
#13200000
0#
#13250000
b100 !
b100 )
b11 %
1#
#13300000
0#
#13350000
b100 %
b110 !
b110 )
1#
#13400000
0#
#13450000
b1000 !
b1000 )
b101 %
1#
#13500000
0#
#13550000
b110 %
b1010 !
b1010 )
1#
#13600000
0#
#13650000
b1100 !
b1100 )
b111 %
1#
#13700000
0#
#13750000
b1000 %
b1110 !
b1110 )
1#
#13800000
0#
#13850000
b10000 !
b10000 )
b1001 %
1#
#13900000
0#
#13950000
b1010 %
b10010 !
b10010 )
1#
#14000000
0#
#14050000
b10100 !
b10100 )
b1011 %
1#
#14100000
0#
#14150000
b1100 %
b10110 !
b10110 )
1#
#14200000
0#
#14250000
b11000 !
b11000 )
b1101 %
1#
#14300000
0#
#14350000
b1110 %
b11010 !
b11010 )
1#
#14400000
0#
#14450000
b11100 !
b11100 )
b1111 %
1#
#14500000
0#
#14550000
b10000 %
b11110 !
b11110 )
1#
#14600000
0#
#14650000
b100000 !
b100000 )
b10001 %
1#
#14700000
0#
#14750000
b10010 %
b100010 !
b100010 )
1#
#14800000
0#
#14850000
b100100 !
b100100 )
b10011 %
1#
#14900000
0#
#14950000
b10100 %
b100110 !
b100110 )
1#
#15000000
0#
#15050000
b101000 !
b101000 )
b10101 %
1#
#15100000
0#
#15150000
b10110 %
b101010 !
b101010 )
1#
#15200000
0#
#15250000
b101100 !
b101100 )
b10111 %
1#
#15300000
0#
#15350000
b11000 %
b101110 !
b101110 )
1#
#15400000
0#
#15450000
b110000 !
b110000 )
b11001 %
1#
#15500000
0#
#15550000
b11010 %
b110010 !
b110010 )
1#
#15600000
0#
#15650000
b110100 !
b110100 )
b11011 %
1#
#15700000
0#
#15750000
b11100 %
b110110 !
b110110 )
1#
#15800000
0#
#15850000
b111000 !
b111000 )
b11101 %
1#
#15900000
0#
#15950000
b11110 %
b111010 !
b111010 )
1#
#16000000
0#
#16050000
b111100 !
b111100 )
b11111 %
1#
#16100000
0#
#16150000
b100000 %
b111110 !
b111110 )
1#
#16200000
0#
#16250000
b1000000 !
b1000000 )
b100001 %
1#
#16300000
0#
#16350000
b100010 %
b1000010 !
b1000010 )
1#
#16400000
0#
#16450000
b1000100 !
b1000100 )
b100011 %
1#
#16500000
0#
#16550000
b100100 %
b1000110 !
b1000110 )
1#
#16600000
0#
#16650000
b1001000 !
b1001000 )
b100101 %
1#
#16700000
0#
#16750000
b100110 %
b1001010 !
b1001010 )
1#
#16800000
0#
#16850000
b1001100 !
b1001100 )
b100111 %
1#
#16900000
0#
#16950000
b101000 %
b1001110 !
b1001110 )
1#
#17000000
0#
#17050000
b1010000 !
b1010000 )
b101001 %
1#
#17100000
0#
#17150000
b101010 %
b1010010 !
b1010010 )
1#
#17200000
0#
#17250000
b1010100 !
b1010100 )
b101011 %
1#
#17300000
0#
#17350000
b101100 %
b1010110 !
b1010110 )
1#
#17400000
0#
#17450000
b1011000 !
b1011000 )
b101101 %
1#
#17500000
0#
#17550000
b101110 %
b1011010 !
b1011010 )
1#
#17600000
0#
#17650000
b1011100 !
b1011100 )
b101111 %
1#
#17700000
0#
#17750000
b110000 %
b1011110 !
b1011110 )
1#
#17800000
0#
#17850000
b1100000 !
b1100000 )
b110001 %
1#
#17900000
0#
#17950000
b110010 %
b1100010 !
b1100010 )
1#
#18000000
0#
#18050000
b1100100 !
b1100100 )
b110011 %
1#
#18100000
0#
#18150000
b110100 %
b1100110 !
b1100110 )
1#
#18200000
0#
#18250000
b1101000 !
b1101000 )
b110101 %
1#
#18300000
0#
#18350000
b110110 %
b1101010 !
b1101010 )
1#
#18400000
0#
#18450000
b1101100 !
b1101100 )
b110111 %
1#
#18500000
0#
#18550000
b111000 %
b1101110 !
b1101110 )
1#
#18600000
0#
#18650000
b1110000 !
b1110000 )
b111001 %
1#
#18700000
0#
#18750000
b111010 %
b1110010 !
b1110010 )
1#
#18800000
0#
#18850000
b1110100 !
b1110100 )
b111011 %
1#
#18900000
0#
#18950000
b111100 %
b1110110 !
b1110110 )
1#
#19000000
0#
#19050000
b1111000 !
b1111000 )
b111101 %
1#
#19100000
0#
#19150000
b111110 %
b1111010 !
b1111010 )
1#
#19200000
0#
#19250000
b1111100 !
b1111100 )
b111111 %
1#
#19300000
0#
#19350000
b1000000 %
b1111110 !
b1111110 )
1#
#19400000
0#
#19450000
b10000000 !
b10000000 )
b1000000 "
b1000000 &
b1000000 '
b1000001 %
1#
#19500000
0#
#19550000
b1000010 %
b1111110 !
b1111110 )
1#
#19600000
0#
#19650000
b1111100 !
b1111100 )
b1000011 %
1#
#19700000
0#
#19750000
b1000100 %
b1111010 !
b1111010 )
1#
#19800000
0#
#19850000
b1111000 !
b1111000 )
b1000101 %
1#
#19900000
0#
#19950000
b1000110 %
b1110110 !
b1110110 )
1#
#20000000
0#
#20050000
b1110100 !
b1110100 )
b1000111 %
1#
#20100000
0#
#20150000
b1001000 %
b1110010 !
b1110010 )
1#
#20200000
0#
#20250000
b1110000 !
b1110000 )
b1001001 %
1#
#20300000
0#
#20350000
b1001010 %
b1101110 !
b1101110 )
1#
#20400000
0#
#20450000
b1101100 !
b1101100 )
b1001011 %
1#
#20500000
0#
#20550000
b1001100 %
b1101010 !
b1101010 )
1#
#20600000
0#
#20650000
b1101000 !
b1101000 )
b1001101 %
1#
#20700000
0#
#20750000
b1001110 %
b1100110 !
b1100110 )
1#
#20800000
0#
#20850000
b1100100 !
b1100100 )
b1001111 %
1#
#20900000
0#
#20950000
b1010000 %
b1100010 !
b1100010 )
1#
#21000000
0#
#21050000
b1100000 !
b1100000 )
b1010001 %
1#
#21100000
0#
#21150000
b1010010 %
b1011110 !
b1011110 )
1#
#21200000
0#
#21250000
b1011100 !
b1011100 )
b1010011 %
1#
#21300000
0#
#21350000
b1010100 %
b1011010 !
b1011010 )
1#
#21400000
0#
#21450000
b1011000 !
b1011000 )
b1010101 %
1#
#21500000
0#
#21550000
b1010110 %
b1010110 !
b1010110 )
1#
#21600000
0#
#21650000
b1010100 !
b1010100 )
b1010111 %
1#
#21700000
0#
#21750000
b1011000 %
b1010010 !
b1010010 )
1#
#21800000
0#
#21850000
b1010000 !
b1010000 )
b1011001 %
1#
#21900000
0#
#21950000
b1011010 %
b1001110 !
b1001110 )
1#
#22000000
0#
#22050000
b1001100 !
b1001100 )
b1011011 %
1#
#22100000
0#
#22150000
b1011100 %
b1001010 !
b1001010 )
1#
#22200000
0#
#22250000
b1001000 !
b1001000 )
b1011101 %
1#
#22300000
0#
#22350000
b1011110 %
b1000110 !
b1000110 )
1#
#22400000
0#
#22450000
b1000100 !
b1000100 )
b1011111 %
1#
#22500000
0#
#22550000
b1100000 %
b1000010 !
b1000010 )
1#
#22600000
0#
#22650000
b1000000 !
b1000000 )
b1100001 %
1#
#22700000
0#
#22750000
b1100010 %
b111110 !
b111110 )
1#
#22800000
0#
#22850000
b111100 !
b111100 )
b1100011 %
1#
#22900000
0#
#22950000
b1100100 %
b111010 !
b111010 )
1#
#23000000
0#
#23050000
b111000 !
b111000 )
b1100101 %
1#
#23100000
0#
#23150000
b1100110 %
b110110 !
b110110 )
1#
#23200000
0#
#23250000
b110100 !
b110100 )
b1100111 %
1#
#23300000
0#
#23350000
b1101000 %
b110010 !
b110010 )
1#
#23400000
0#
#23450000
b110000 !
b110000 )
b1101001 %
1#
#23500000
0#
#23550000
b1101010 %
b101110 !
b101110 )
1#
#23600000
0#
#23650000
b101100 !
b101100 )
b1101011 %
1#
#23700000
0#
#23750000
b1101100 %
b101010 !
b101010 )
1#
#23800000
0#
#23850000
b101000 !
b101000 )
b1101101 %
1#
#23900000
0#
#23950000
b1101110 %
b100110 !
b100110 )
1#
#24000000
0#
#24050000
b100100 !
b100100 )
b1101111 %
1#
#24100000
0#
#24150000
b1110000 %
b100010 !
b100010 )
1#
#24200000
0#
#24250000
b100000 !
b100000 )
b1110001 %
1#
#24300000
0#
#24350000
b1110010 %
b11110 !
b11110 )
1#
#24400000
0#
#24450000
b11100 !
b11100 )
b1110011 %
1#
#24500000
0#
#24550000
b1110100 %
b11010 !
b11010 )
1#
#24600000
0#
#24650000
b11000 !
b11000 )
b1110101 %
1#
#24700000
0#
#24750000
b1110110 %
b10110 !
b10110 )
1#
#24800000
0#
#24850000
b10100 !
b10100 )
b1110111 %
1#
#24900000
0#
#24950000
b1111000 %
b10010 !
b10010 )
1#
#25000000
0#
#25050000
b10000 !
b10000 )
b1111001 %
1#
#25100000
0#
#25150000
b1111010 %
b1110 !
b1110 )
1#
#25200000
0#
#25250000
b1100 !
b1100 )
b1111011 %
1#
#25300000
0#
#25350000
b1111100 %
b1010 !
b1010 )
1#
#25400000
0#
#25450000
b1000 !
b1000 )
b1111101 %
1#
#25500000
0#
#25550000
b1111110 %
b110 !
b110 )
1#
#25600000
0#
#25650000
b100 !
b100 )
b1111111 %
1#
#25700000
0#
#25750000
b0 %
b10 !
b10 )
1#
#25800000
0#
#25850000
b0 !
b0 )
b11000000 "
b11000000 &
b11000000 '
b1 %
1#
#25900000
0#
#25950000
b10 %
b10 !
b10 )
1#
#26000000
0#
#26050000
b100 !
b100 )
b11 %
1#
#26100000
0#
#26150000
b100 %
b110 !
b110 )
1#
#26200000
0#
#26250000
b1000 !
b1000 )
b101 %
1#
#26300000
0#
#26350000
b110 %
b1010 !
b1010 )
1#
#26400000
0#
#26450000
b1100 !
b1100 )
b111 %
1#
#26500000
0#
#26550000
b1000 %
b1110 !
b1110 )
1#
#26600000
0#
#26650000
b10000 !
b10000 )
b1001 %
1#
#26700000
0#
#26750000
b1010 %
b10010 !
b10010 )
1#
#26800000
0#
#26850000
b10100 !
b10100 )
b1011 %
1#
#26900000
0#
#26950000
b1100 %
b10110 !
b10110 )
1#
#27000000
0#
#27050000
b11000 !
b11000 )
b1101 %
1#
#27100000
0#
#27150000
b1110 %
b11010 !
b11010 )
1#
#27200000
0#
#27250000
b11100 !
b11100 )
b1111 %
1#
#27300000
0#
#27350000
b10000 %
b11110 !
b11110 )
1#
#27400000
0#
#27450000
b100000 !
b100000 )
b10001 %
1#
#27500000
0#
#27550000
b10010 %
b100010 !
b100010 )
1#
#27600000
0#
#27650000
b100100 !
b100100 )
b10011 %
1#
#27700000
0#
#27750000
b10100 %
b100110 !
b100110 )
1#
#27800000
0#
#27850000
b101000 !
b101000 )
b10101 %
1#
#27900000
0#
#27950000
b10110 %
b101010 !
b101010 )
1#
#28000000
0#
#28050000
b101100 !
b101100 )
b10111 %
1#
#28100000
0#
#28150000
b11000 %
b101110 !
b101110 )
1#
#28200000
0#
#28250000
b110000 !
b110000 )
b11001 %
1#
#28300000
0#
#28350000
b11010 %
b110010 !
b110010 )
1#
#28400000
0#
#28450000
b110100 !
b110100 )
b11011 %
1#
#28500000
0#
#28550000
b11100 %
b110110 !
b110110 )
1#
#28600000
0#
#28650000
b111000 !
b111000 )
b11101 %
1#
#28700000
0#
#28750000
b11110 %
b111010 !
b111010 )
1#
#28800000
0#
#28850000
b111100 !
b111100 )
b11111 %
1#
#28900000
0#
#28950000
b100000 %
b111110 !
b111110 )
1#
#29000000
0#
#29050000
b1000000 !
b1000000 )
b100001 %
1#
#29100000
0#
#29150000
b100010 %
b1000010 !
b1000010 )
1#
#29200000
0#
#29250000
b1000100 !
b1000100 )
b100011 %
1#
#29300000
0#
#29350000
b100100 %
b1000110 !
b1000110 )
1#
#29400000
0#
#29450000
b1001000 !
b1001000 )
b100101 %
1#
#29500000
0#
#29550000
b100110 %
b1001010 !
b1001010 )
1#
#29600000
0#
#29650000
b1001100 !
b1001100 )
b100111 %
1#
#29700000
0#
#29750000
b101000 %
b1001110 !
b1001110 )
1#
#29800000
0#
#29850000
b1010000 !
b1010000 )
b101001 %
1#
#29900000
0#
#29950000
b101010 %
b1010010 !
b1010010 )
1#
#30000000
0#
#30050000
b1010100 !
b1010100 )
b101011 %
1#
#30100000
0#
#30150000
b101100 %
b1010110 !
b1010110 )
1#
#30200000
0#
#30250000
b1011000 !
b1011000 )
b101101 %
1#
#30300000
0#
#30350000
b101110 %
b1011010 !
b1011010 )
1#
#30400000
0#
#30450000
b1011100 !
b1011100 )
b101111 %
1#
#30500000
0#
#30550000
b110000 %
b1011110 !
b1011110 )
1#
#30600000
0#
#30650000
b1100000 !
b1100000 )
b110001 %
1#
#30700000
0#
#30750000
b110010 %
b1100010 !
b1100010 )
1#
#30800000
0#
#30850000
b1100100 !
b1100100 )
b110011 %
1#
#30900000
0#
#30950000
b110100 %
b1100110 !
b1100110 )
1#
#31000000
0#
#31050000
b1101000 !
b1101000 )
b110101 %
1#
#31100000
0#
#31150000
b110110 %
b1101010 !
b1101010 )
1#
#31200000
0#
#31250000
b1101100 !
b1101100 )
b110111 %
1#
#31300000
0#
#31350000
b111000 %
b1101110 !
b1101110 )
1#
#31400000
0#
#31450000
b1110000 !
b1110000 )
b111001 %
1#
#31500000
0#
#31550000
b111010 %
b1110010 !
b1110010 )
1#
#31600000
0#
#31650000
b1110100 !
b1110100 )
b111011 %
1#
#31700000
0#
#31750000
b111100 %
b1110110 !
b1110110 )
1#
#31800000
0#
#31850000
b1111000 !
b1111000 )
b111101 %
1#
#31900000
0#
#31950000
b111110 %
b1111010 !
b1111010 )
1#
#32000000
0#
#32050000
b1111100 !
b1111100 )
b111111 %
1#
#32100000
0#
#32150000
b1000000 %
b1111110 !
b1111110 )
1#
#32200000
0#
#32250000
b10000000 !
b10000000 )
b1000000 "
b1000000 &
b1000000 '
b1000001 %
1#
#32300000
0#
#32350000
b1000010 %
b1111110 !
b1111110 )
1#
#32400000
0#
#32450000
b1111100 !
b1111100 )
b1000011 %
1#
#32500000
0#
#32550000
b1000100 %
b1111010 !
b1111010 )
1#
#32600000
0#
#32650000
b1111000 !
b1111000 )
b1000101 %
1#
#32700000
0#
#32750000
b1000110 %
b1110110 !
b1110110 )
1#
#32800000
0#
#32850000
b1110100 !
b1110100 )
b1000111 %
1#
#32900000
0#
#32950000
b1001000 %
b1110010 !
b1110010 )
1#
#33000000
0#
#33050000
b1110000 !
b1110000 )
b1001001 %
1#
#33100000
0#
#33150000
b1001010 %
b1101110 !
b1101110 )
1#
#33200000
0#
#33250000
b1101100 !
b1101100 )
b1001011 %
1#
#33300000
0#
#33350000
b1001100 %
b1101010 !
b1101010 )
1#
#33400000
0#
#33450000
b1101000 !
b1101000 )
b1001101 %
1#
#33500000
0#
#33550000
b1001110 %
b1100110 !
b1100110 )
1#
#33600000
0#
#33650000
b1100100 !
b1100100 )
b1001111 %
1#
#33700000
0#
#33750000
b1010000 %
b1100010 !
b1100010 )
1#
#33800000
0#
#33850000
b1100000 !
b1100000 )
b1010001 %
1#
#33900000
0#
#33950000
b1010010 %
b1011110 !
b1011110 )
1#
#34000000
0#
#34050000
b1011100 !
b1011100 )
b1010011 %
1#
#34100000
0#
#34150000
b1010100 %
b1011010 !
b1011010 )
1#
#34200000
0#
#34250000
b1011000 !
b1011000 )
b1010101 %
1#
#34300000
0#
#34350000
b1010110 %
b1010110 !
b1010110 )
1#
#34400000
0#
#34450000
b1010100 !
b1010100 )
b1010111 %
1#
#34500000
0#
#34550000
b1011000 %
b1010010 !
b1010010 )
1#
#34600000
0#
#34650000
b1010000 !
b1010000 )
b1011001 %
1#
#34700000
0#
#34750000
b1011010 %
b1001110 !
b1001110 )
1#
#34800000
0#
#34850000
b1001100 !
b1001100 )
b1011011 %
1#
#34900000
0#
#34950000
b1011100 %
b1001010 !
b1001010 )
1#
#35000000
0#
#35050000
b1001000 !
b1001000 )
b1011101 %
1#
#35100000
0#
#35150000
b1011110 %
b1000110 !
b1000110 )
1#
#35200000
0#
#35250000
b1000100 !
b1000100 )
b1011111 %
1#
#35300000
0#
#35350000
b1100000 %
b1000010 !
b1000010 )
1#
#35400000
0#
#35450000
b1000000 !
b1000000 )
b1100001 %
1#
#35500000
0#
#35550000
b1100010 %
b111110 !
b111110 )
1#
#35600000
0#
#35650000
b111100 !
b111100 )
b1100011 %
1#
#35700000
0#
#35750000
b1100100 %
b111010 !
b111010 )
1#
#35800000
0#
#35850000
b111000 !
b111000 )
b1100101 %
1#
#35900000
0#
#35950000
b1100110 %
b110110 !
b110110 )
1#
#36000000
0#
#36050000
b110100 !
b110100 )
b1100111 %
1#
#36100000
0#
#36150000
b1101000 %
b110010 !
b110010 )
1#
#36200000
0#
#36250000
b110000 !
b110000 )
b1101001 %
1#
#36300000
0#
#36350000
b1101010 %
b101110 !
b101110 )
1#
#36400000
0#
#36450000
b101100 !
b101100 )
b1101011 %
1#
#36500000
0#
#36550000
b1101100 %
b101010 !
b101010 )
1#
#36600000
0#
#36650000
b101000 !
b101000 )
b1101101 %
1#
#36700000
0#
#36750000
b1101110 %
b100110 !
b100110 )
1#
#36800000
0#
#36850000
b100100 !
b100100 )
b1101111 %
1#
#36900000
0#
#36950000
b1110000 %
b100010 !
b100010 )
1#
#37000000
0#
#37050000
b100000 !
b100000 )
b1110001 %
1#
#37100000
0#
#37150000
b1110010 %
b11110 !
b11110 )
1#
#37200000
0#
#37250000
b11100 !
b11100 )
b1110011 %
1#
#37300000
0#
#37350000
b1110100 %
b11010 !
b11010 )
1#
#37400000
0#
#37450000
b11000 !
b11000 )
b1110101 %
1#
#37500000
0#
#37550000
b1110110 %
b10110 !
b10110 )
1#
#37600000
0#
#37650000
b10100 !
b10100 )
b1110111 %
1#
#37700000
0#
#37750000
b1111000 %
b10010 !
b10010 )
1#
#37800000
0#
#37850000
b10000 !
b10000 )
b1111001 %
1#
#37900000
0#
#37950000
b1111010 %
b1110 !
b1110 )
1#
#38000000
0#
#38050000
b1100 !
b1100 )
b1111011 %
1#
#38100000
0#
#38150000
b1111100 %
b1010 !
b1010 )
1#
#38200000
0#
#38250000
b1000 !
b1000 )
b1111101 %
1#
#38300000
0#
#38350000
b1111110 %
b110 !
b110 )
1#
#38400000
0#
#38450000
b100 !
b100 )
b1111111 %
1#
#38500000
0#
#38550000
b0 %
b10 !
b10 )
1#
#38600000
0#
#38650000
b0 !
b0 )
b11000000 "
b11000000 &
b11000000 '
b1 %
1#
#38700000
0#
#38750000
b10 %
b10 !
b10 )
1#
#38800000
0#
#38850000
b100 !
b100 )
b11 %
1#
#38900000
0#
#38950000
b100 %
b110 !
b110 )
1#
#39000000
0#
#39050000
b1000 !
b1000 )
b101 %
1#
#39100000
0#
